Workbook
Name Slicer_City__Location: #N/A
Name Slicer_City__Location1: #N/A
Name Slicer_Industry_Vertical: #N/A
Name Slicer_Year: #N/A

Sheet README
A1: INDIAN STARTUP FUNDING ANALYSIS (2015–2020)
A6: Project Overview
A7: This project analyzes Indian startup funding data from 2015 to 2020
A8: to identify funding trends, industry performance, investor dominance,
A9: and city-wise capital distribution using Microsoft Excel.
A11: The analysis includes pivot-based summaries, lookup enrichment,
A12: and an interactive executive dashboard.
A14: Project Objectives
A15: • Analyze total funding trends over time
A16: • Identify top industries attracting investment
A17: • Determine leading investors by funding amount
A18: • Compare Angel vs VC funding contribution
... A45: Data Analytics Portfolio Project

Sheet Raw_data
A1: Sr No | B1: Date dd/mm/yyyy | C1: Startup Name | D1: Industry Vertical | E1: SubVertical | F1: City Location | G1: Investors Name | H1: InvestmentnType | I1: Amount in USD | J1: Remarks
A2: 1 | B2: 43839 | C2: BYJU’S | D2: E-Tech | E2: E-learning | F2: Bengaluru | G2: Tiger Global Management | H2: Private Equity Round | I2: 200000000
A3: 2 | B3: 43843 | C3: Shuttl | D3: Transportation | E3: App based shuttle service | F3: Gurgaon | G3: Susquehanna Growth Equity | H3: Series C | I3: 8048394
A4: 3 | B4: 43839 | C4: Mamaearth | D4: E-commerce | E4: Retailer of baby and toddler products | F4: Bengaluru | G4: Sequoia Capital India | H4: Series B | I4: 18358860
A5: 4 | B5: 43832 | C5: https://www.wealthbucket.in/ | D5: FinTech | E5: Online Investment | F5: New Delhi | G5: Vinod Khatumal | H5: Pre-series A | I5: 3000000
A6: 5 | B6: 43832 | C6: Fashor | D6: Fashion and Apparel | E6: Embroiled Clothes For Women | F6: Mumbai | G6: Sprout Venture Partners | H6: Seed Round | I6: 1800000
A7: 6 | B7: 43843 | C7: Pando | D7: Logistics | E7: Open-market, freight management platform | F7: Chennai | G7: Chiratae Ventures | H7: Series A | I7: 9000000
A8: 7 | B8: 43840 | C8: Zomato | D8: Hospitality | E8: Online Food Delivery Platform | F8: Gurgaon | G8: Ant Financial | H8: Private Equity Round | I8: 150000000
A9: 8 | B9: 43811 | C9: Ecozen | D9: Technology | E9: Agritech | F9: Pune | G9: Sathguru Catalyzer Advisors | H9: Series A | I9: 6000000
A10: 9 | B10: 43805 | C10: CarDekho | D10: E-Commerce | E10: Automobile | F10: Gurgaon | G10: Ping An Global Voyager Fund | H10: Series D | I10: 70000000
A11: 10 | B11: 43802 | C11: Dhruva Space | D11: Aerospace | E11: Satellite Communication | F11: Bengaluru | G11: Mumbai Angels, Ravikanth Reddy | H11: Seed | I11: 50000000
A12: 11 | B12: 43812 | C12: Rivigo | D12: Technology | E12: Logistics Services and Solutions | F12: Gurgaon | G12: SAIF Partners, Spring Canter Investment Ltd. | H12: Series F | I12: 20000000
A13: 12 | B13: 43816 | C13: Healthians | D13: B2B-focused foodtech startup | E13: Food Solutions For Corporate | F13: Bengaluru | G13: Paytm, NPTK, Sabre Partners and Neoplux | H13: Series C | I13: 12000000
A14: 13 | B14: 43815 | C14: Licious | D14: E-Commerce | E14: Online Meat And Seafood Ordering Startup | F14: Bengaluru | G14: Vertex Growth Fund | H14: Series E | I14: 30000000
A15: 14 | B15: 43815 | C15: InCred | D15: Finance | E15: Non-Banking Financial Company | F15: Mumbai | H15: Debt Funding | I15: 5900000
A16: 15 | B16: 43813 | C16: Trell | D16: Video | E16: Experience Discovery Platform | F16: Bengaluru | G16: Ruizheng Investment | H16: Seed Round | I16: 2000000
A17: 16 | B17: 43810 | C17: Rein Games | D17: Gaming | E17: Real money based gaming startup | F17: Noida | G17: Manipal Education and Medical Group (MEMG) | H17: Seed Round | I17: 50000000
A18: 17 | B18: 43819 | C18: Lenskart.com | D18: E-Commerce | E18: Online Eyewear Shopping Portal | F18: Faridabad | G18: SoftBank Vision Fund | H18: Series G | I18: 231000000
A19: 18 | B19: 43782 | C19: Freshworks | D19: Software | E19: Business and customer engagement tools | F19: San Francisco | G19: Sequoia, CapitalG, Accel | H19: Series H | I19: 150000000
A20: 19 | B20: 43783 | C20: Misters | D20: Health and wellness | E20: Men's Health and Wellness brand | F20: Gurgaon | G20: Sauce.vc, Rainforest Ventures | H20: Series B | I20: 486000
A21: 20 | B21: 43782 | C21: Sunstone Eduversity Pvt. Ltd | D21: Education | E21: Elearning | F21: Gurgaon | G21: Prime Venture Partners, LetsVenture, PS1 Venture and GlobalLogic co-founder Rajul Garg | H21: Seed | I21: 1500000
A22: 21 | B22: 43786 | C22: Burger Singh | D22: Food and Beverage | E22: Indian Burger Brand | F22: Gurgaon | G22: RB Investments | H22: Venture | I22: undisclosed
A23: 22 | B23: 43787 | C23: Healthians | D23: Health and Wellness | E23: Healthcare services | F23: Gurgaon | G23: DG Daiwa Ventures, DG Incubation | H23: Series B | I23: 12000000
A24: 23 | B24: 43784 | C24: Ninjacart | D24: B2B Marketing | E24: Agritech | F24: Bengaluru | G24: Trifecta Capital Advisors | H24: Debt Funding | I24: 26000000
A25: 24 | B25: 43789 | C25: Aye Finance | D25: FinTech | E25: Financial Services To MSMEs | F25: Gurgaon | G25: FinTech | H25: Debt Funding | I25: 17411265
A26: 25 | B26: 43781 | C26: SuperGaming | D26: Video Games | E26: Social gaming platform | F26: Pune | G26: Dream Incubator | H26: Seed Funding | I26: 1300000
A27: 26 | B27: 43789 | C27: Clumio | D27: SaaS | E27: Recovery software | F27: San Jose, | G27: Altimeter Capital, Sutter Hill Ventures | H27: Series C | I27: 135000000
A28: 27 | B28: 43780 | C28: eBikeGo | D28: Last Mile Transportation | E28: Electric bike rental | F28: Amritsar | G28: Startup Buddy | H28: Seed | I28: 300000
A29: 28 | B29: 43788 | C29: Digital Mall Asia | D29: E-Commerce | E29: Virtual e-commerce platform | F29: Delhi | G29: Amour Infrastructure | H29: Seed Funding | I29: 220000000
A30: 29 | B30: 43787 | C30: Medikabazaar | D30: Healthcare | E30: B2B platform for medical supplies | F30: Mumbai | G30: Ackermans & van Haaren, HealthQuad, Rebright Partners, Toppan Printing | H30: Series B | I30: 15800000
A31: 30 | B31: 43784 | C31: Vogo Automotive | D31: Last Mile Transportation | E31: Scooter sharing app | F31: Kormangala | G31: Matrix Partners, Stellaris Venture Partners, Kalaari Capital | H31: Series B | I31: 283000000
A32: 31 | B32: 43788 | C32: Furtados School of Music | D32: Education | E32: Music Education | F32: Tulangan | G32: IAN Fund and DSG Consumer Partners | I32: 200000000
A33: 32 | B33: 43794 | C33: Paytm | D33: FinTech | E33: Mobile Wallet | F33: Noida | G33: Vijay Shekhar Sharma | H33: Funding Round | I33: 1000000000
A34: 33 | B34: 43742 | C34: Dunzo | D34: Customer Service | E34: Delivery Service | F34: Bengaluru | G34: Lightbox | H34: Series D | I34: 45000000
A35: 34 | B35: 43740 | C35: Udaan | D35: B2B | E35: Business development | F35: Bengaluru | G35: Altimeter Capital, DST Global | H35: Series D | I35: 585000000
A36: 35 | B36: 43759 | C36: The Man Company | D36: Consumer Goods | E36: Beauty and Grooming | F36: Gurgaon | G36: Ayushmann Khurana | H36: Corporate Round | I36: unknown
A37: 36 | B37: 43713 | C37: FPL Technologies | D37: FinTech | E37: Financial Services | F37: Pune | G37: Matrix Partners India, Sequoia India | H37: Maiden Round | I37: 4500000
A38: 37 | B38: 43712 | C38: Cashflo | D38: FinTech | E38: Invoice discounting platform and SME lending marketplace | F38: Mumbai | G38: SAIF Partners | H38: Series A | I38: 3300000
A39: 38 | B39: 43712 | C39: Digital F5 | D39: Advertising, Marketing | E39: Digital marketing firm | F39: Mumbai | G39: TIW Private Equity | H39: Private Equity Round | I39: 6000000
A40: 39 | B40: 43712 | C40: 3rdFlix | D40: SaaS | E40: Education Technology | F40: Hyderabad | G40: Exfinity Venture Partners | H40: pre-series A | I40: 5000000
A41: 40 | B41: 43712 | C41: 75F | D41: IoT | E41: Building automation system | F41: Burnsville | G41: Breakthrough Energy Ventures | H41: Series A | I41: 18000000
A42: 41 | B42: 43712 | C42: Myelin Foundry | D42: Information Technology | E42: Deep-technology | F42: Bengaluru | G42: Endiya Partners | H42: Seed | I42: 1000000
A43: 42 | B43: 43712 | C43: Atomberg Technology | D43: Consumer Technology | E43: Consumer Electronics, Home Appliances | F43: Mumbai | G43: A91 Partners | H43: Series A | I43: 10000000
A44: 43 | B44: 43712 | C44: GOQii | D44: Health and Wellness | E44: Wearable Fitness Bands | F44: Menlo Park | G44: Bennett Coleman and Company Ltd (BCCL) | H44: Series C | I44: 450000000
A45: 44 | B45: 43711 | C45: Vyapar App | D45: Accounting | E45: Mobile-based Accounting Software | F45: Bengaluru | G45: India Quotient, Axilor Ventures | H45: Series A | I45: 5000000
A46: 45 | B46: 43678 | C46: CarDekho | D46: E-Commerce | E46: Automotive | F46: Gurgaon | G46: SC GG India Mobility Holdings LLC | H46: Series C | I46: 20000000 | J46: nan
A47: 46 | B47: 43678 | C47: Progcap | D47: Finance | E47: Supply Chain Management | F47: New Delhi | G47: Sequoia India | H47: Series A | I47: 5000000 | J47: nan
A48: 47 | B48: 43678 | C48: MyPetrolPump | D48: Retail | E48: Fuel Delivery | F48: Bengaluru | H48: Seed Funding Round | I48: 1600000 | J48: nan
A49: 48 | B49: 43678 | C49: Alteria Capital | D49: Finance | E49: VC Funds | F49: Mumbai | G49: Azim Premji, Binny Bansal | H49: Single Venture | I49: 140000000 | J49: nan
A50: 49 | B50: 43678 | C50: Pine Labs | D50: Information Technology | E50: Last-mile retail transaction technology | F50: Noida | G50: Pine Labs Pte Ltd | H50: Corporate Round | I50: 38080000 | J50: nan
A51: 50 | B51: 43689 | C51: Meesho | D51: E-Commerce | E51: Social Commerce | F51: Bengaluru | G51: Naspers | H51: Series D | I51: 125000000 | J51: nan
A52: 51 | B52: 43690 | C52: Cars24 | D52: E-Commerce | E52: Car Retail | F52: Gurugram | G52: MS Dhoni | H52: Series D | I52: 11000000 | J52: nan
A53: 52 | B53: 43690 | C53: Uniphore | D53: Customer Service Platform | E53: Conversational AI | F53: Palo Alto | G53: March Capital Partners | H53: Series C | I53: 51000000 | J53: nan
A54: 53 | B54: 43700 | C54: Zendrive | D54: Automotive | E54: Road Safety Analytics | F54: San Francisco | G54: XL Innovate | H54: Series B | I54: 37000000 | J54: nan
A55: 54 | B55: 43700 | C55: Lo! Foods | D55: Consumer Goods | E55: Low carb food for Diabetics | F55: Bengaluru | G55: Rashmi Daga (founder, FreshMenu), Raveen Sastry (co-founder, Myntra) and Mitesh Shah (finance chief, BookMyShow) | H55: Seed Round | I55: 500000 | J55: nan
A56: 55 | B56: 43700 | C56: Tala | D56: FinTech | E56: Digital Lending Platform | F56: Santa Monica | G56: RPS Ventures | H56: Series D | I56: 110000000 | J56: nan
A57: 56 | B57: 43699 | C57: INDwealth | D57: FinTech | E57: Wealth Management | F57: Gurgaon | G57: Tiger Global Management | H57: Venture Round | I57: 15000000 | J57: nan
A58: 57 | B58: 43698 | C58: HungerBox | D58: Food and Beverage | E58: B2B Foodtech | F58: Bengaluru | G58: One97 Communications Ltd. | H58: Series C | I58: 6590000 | J58: nan
A59: 58 | B59: 43700 | C59: AdmitKard | D59: EdTech | E59: University Admissions | F59: Noida | G59: Growth DNA | H59: Seed Round | I59: 1000000 | J59: nan
A60: 59 | B60: 43696 | C60: Mishry Reviews | D60: Services | E60: Product Review | F60: Gurgaon | G60: Vir Sanghvi | H60: Series A | I60: Undisclosed | J60: nan
A61: 60 | B61: 43696 | C61: Grofers | D61: E-Commerce | E61: Grocery Delivery | F61: Gurgaon | G61: Softbank Vision Fund | H61: Series F | I61: 70000000 | J61: nan
A62: 61 | B62: 43704 | C62: Rapido Bike Taxi | D62: Transportation | E62: Bike Taxi | F62: Bengaluru | G62: Westbridge Capital | H62: Series B | I62: 3900000000 | J62: nan
A63: 62 | B63: 43648 | C63: RenewBuy | D63: Finance | E63: Auto Insurance | F63: Gurgaon | G63: Lok Capital, IIFL Wealth | H63: Series B | I63: 19000000 | J63: nan
A64: 63 | B64: 43648 | C64: Atlan | D64: Information Technology | E64: Big Data | F64: Singapore | G64: WaterBridge Ventures | H64: Pre-Series A | I64: 2500000 | J64: nan
A65: 64 | B65: 43647 | C65: WizCounsel | D65: Compliance | E65: Consulting | F65: New Delhi | G65: Kapil Dev | H65: Angel | I65: 145000 | J65: nan
A66: 65 | B66: 43649 | C66: Ola Cabs | D66: Transport | E66: Cabs | F66: Kormangala | G66: DIG Investment Ab, Deshe Holdings, Samih Toukan and Hussam Khoury | H66: Series J | I66: 1000000 | J66: nan
A67: 66 | B67: 43647 | C67: Uniphore | D67: Artificial Intelligence | E67: Speech Recognition | F67: Taramani | G67: March Capital Partners | H67: Series C | I67: 38080000 | J67: nan
A68: 67 | B68: 43650 | C68: Daalchini Technologies | D68: Food and Beverage | E68: Digital Vending Machine | F68: New Delhi | G68: Artha Venture | H68: Seed Round | I68: 500000 | J68: nan
A69: 68 | B69: 43656 | C69: "BYJU\\'S" | D69: EdTech | E69: Education | F69: Bengaluru | G69: Qatar Investment Authority | H69: Private Equity Round | I69: 150000000 | J69: nan
A70: 69 | B70: 43657 | C70: Moglix | D70: E-Commerce | E70: Industrial Tools and Equipments | F70: Singapore | G70: Composite Capital Management, Sequoia Capital India, Tiger Global Management | H70: Series D | I70: 60000000 | J70: nan
A71: 70 | B71: 43656 | C71: Ezyhaul | D71: Tech | E71: Logistics | F71: Singapore | G71: Undisclosed | H71: Series B | I71: 16000000 | J71: nan
A72: 71 | B72: 43656 | C72: Indus OS | D72: Tech | E72: Smartphone Operating System | F72: Andheri | G72: Ventureast | H72: Series B | I72: 5750000 | J72: nan
... A77: 76 | B77: 43620 | C77: Bira91 | D77: Food and Beverage | E77: Brewery | F77: New Delhi | G77: Anicut Capital | H77: Debt Funding | I77: 10000000 | J77: nan
A78: 77 | B78: 43619 | C78: FabHotels | D78: E-Commerce | E78: Hospitality | F78: Gurgaon | G78: Goldman Sachs, Accel Partners and Qualcomm | I78: 4889975.5 | J78: nan
A79: 78 | B79: 43619 | C79: Avail Finance | D79: Finance | E79: FinTech | F79: Bengaluru | G79: Matrix Partners | H79: Series A | I79: 9000000 | J79: nan
A80: 79 | B80: 43620 | C80: BharatPe | D80: Finance | E80: FinTech | F80: New Delhi | G80: Insight Partners | H80: Series B | I80: 75000000 | J80: nan
A81: 80 | B81: 43620 | C81: Recykal | D81: Waste Management Service | E81: Optimization | F81: Hyderabad | G81: Triton Investment Advisors, Pidilite Industries director Ajay Parekh | H81: pre-Series A | I81: 26000000 | J81: nan
A82: 81 | B82: 43619 | C82: Agara Labs | D82: Deep-Tech | E82: Artificial Intelligence | F82: Bengaluru | G82: Blume Ventures and RTP Global | H82: pre-Series A | I82: 2500000 | J82: nan
A83: 82 | B83: 43622 | C83: Sistema.bio | D83: Agriculture | E83: Hybrid Reactor Biodigestor | F83: Nairobi | G83: Shell Foundation, DILA CAPITAL, Engie RDE Fund, EcoEnterprise Fund, EDFIMC (ElectriFI), Endeavor Catalyst Fund, CoCapital, Triodos, Alpha Mundi, and Lendahand | I83: 2739034.7 | J83: nan
A84: 83 | B84: 43622 | C84: Chakr Innovation | D84: Energy | E84: Renewable Energy | F84: New Delhi | G84: IAN Fund | H84: Series A | I84: 26000000 | J84: nan
A85: 84 | B85: 43622 | C85: Pratilipi | D85: Digital Media | E85: E-Books | F85: Bengaluru | G85: Qiming Venture Partners | H85: Series B | I85: 15109500 | J85: nan
A86: 85 | B86: 43626 | C86: Bolo App | D86: Digital Media | E86: Video Platform | F86: Bengaluru | G86: Nexus Venture Partners | H86: Seed Funding | I86: 430200 | J86: nan
A87: 86 | B87: 43626 | C87: OkCredit | D87: FinTech | E87: Financial Services | F87: Haryana | G87: Tiger Global Management | H87: Series A | I87: 15500000 | J87: nan
A88: 87 | B88: 43622 | C88: Biz2Credit | D88: FinTech | E88: Online Lending Platform | F88: New York | G88: WestBridge Capital | H88: Series B | I88: 52000000 | J88: nan
A89: 88 | B89: 43624 | C89: Vogo Automotive Pvt. Ltd. | D89: Transportation | E89: Dockless Scooter Rental Company | F89: Karnataka | G89: Alteria Capital | H89: Debt Funding | I89: 3584000 | J89: nan
A90: 89 | B90: 43620 | C90: Leegality | D90: Services | E90: Digital Documentation | F90: Mumbai/Bengaluru | G90: Mumbai Angels | H90: Series A | I90: 3400000 | J90: nan
A91: 90 | B91: 43591 | C91: Ola Electric | D91: Transport | E91: Cabs | F91: Bengaluru | G91: Tata Sons | H91: Series A | I91: undisclosed | J91: nan
A92: 91 | B92: 43591 | C92: Saahas Zero Waste | D92: Waste Management Service | E92: Optimization | F92: Bengaluru | G92: C4D Partners | H92: Venture - Series Unknown | I92: 868600 | J92: nan
A93: 92 | B93: 43590 | C93: StyleDotMe | D93: E-commerce | E93: Fashion and Shopping | F93: Delhi | G93: Indian Angel Network and other angel investors, Innov8 founder Ritesh Malik, Josh Talks founders Supriya Paul and Shobha Banga, and former Hero Corporate president Rohit Chanana | H93: Bridge Round | I93: undisclosed | J93: nan
A94: 93 | B94: 43586 | C94: BlackBuck | D94: Transport | E94: Logistics | F94: Bengaluru | G94: Goldman Sachs Investment Partners and Silicon Valley-based Accel, Wellington, Sequoia Capital, B Capital, LightStreet, Sands Capital and International Finance Corporation, | H94: Series D | I94: 150000000 | J94: nan
A95: 94 | B95: 43587 | C95: Zenoti | D95: Saas | E95: Beauty and Wellness Industry | F95: Hyderabad | G95: Tiger Global Management | H95: Series C | I95: 50000000 | J95: nan
A96: 95 | B96: 43613 | C96: Ather Energy | D96: Automobile | E96: Electric Vehicle | F96: Bengaluru | G96: Sachin Bansal | H96: Series C | I96: 51000000 | J96: nan
A97: 96 | B97: 43613 | C97: FreshVnF | D97: Agtech | E97: Fresh Agriculture Produces | F97: Mumbai | G97: Equanimity Ventures | H97: Seed Round | I97: 140000000 | J97: nan
A98: 97 | B98: 43615 | C98: GlowRoad | D98: E-commerce | E98: Retail | F98: Bengaluru | G98: Korea Investment Partners, Vertex Ventures | H98: Series B | I98: 11500000 | J98: nan
A99: 98 | B99: 43616 | C99: Bira91 | D99: Food and Beverage | E99: Brewery | F99: New Delhi | G99: Sixth Sense Ventures | H99: Series B | I99: 5600000 | J99: nan
A100: 99 | B100: 43571 | C100: Kuvera | D100: Finance | E100: Wealth Management | F100: Bengaluru | G100: Eight Roads | H100: Series A | I100: 45000000 | J100: nan
A101: 100 | B101: 43567 | C101: Medlife | D101: E-commerce | E101: Online Medicine | F101: Bengaluru | G101: Prasid Uno Family Trust | H101: Private Equity | I101: 17000000 | J101: nan
A102: 101 | B102: 43565 | C102: Kabadiwala | D102: E-commerce | E102: Waste Management | F102: Bhopal | G102: Unilever, Beehive Capital Advisor, ABCOM Investments, Parekh Marine Transport, | H102: Private Equity | I102: 430665 | J102: nan
A103: 102 | B103: 43568 | C103: Tripoto | D103: Social Media | E103: Travel | F103: New Delhi | G103: Orchid India, Hornbill Orchid India Fund, Chiratae Ventures (formerly IDG Ventures), 3one4 Capital, Lasmer NV | H103: Series B | I103: 3591375 | J103: nan
A104: 103 | B104: 43567 | C104: Azah | D104: Health and Wellness | E104: Organic wellness | F104: Gurugram | G104: Unnamed angel investors | H104: Seed Funding | I104: 200000 | J104: nan
...

Sheet Data_Cleaning
A1: Sr No. | B1: Date | C1: Startup Name | D1: Industry Vertical | E1: SubVertical | F1: City Location | G1: Investors Name | H1: Investment Type | I1: Amount in USD | J1: Remarks | K1: Funding Range | L1: Startup City | M1: Investor Type | N1: Year
A2: 1 | B2: 43839 | C2: Byju’S | D2: E-Tech | E2: E-Learning | F2: Bangalore | G2: Tiger Global Management | H2: Private Equity Round | I2: 200000000 | J2: N/A | K2: >10M | L2: =IFERROR(_xlfn.XLOOKUP(Table1[[#This Row],[Startup Name]],Reference_Tables!$A$5:$A$3048,Reference_Tables!$B$5:$B$3048,"N/A",0),"N/A") -> Gurugram | M2: =IFERROR(_xlfn.XLOOKUP(Table1[[#This Row],[Investors Name]],Reference_Tables!$E$5:$E$3048,Reference_Tables!$F$5:$F$3048,"N/A",0),"N/A") -> Angel | N2: =YEAR(Table1[[#This Row],[Date]]) -> 2020
A3: 2 | B3: 43843 | C3: Shuttl | D3: Transportation | E3: App Based Shuttle Service | F3: Gurugram | G3: Susquehanna Growth Equity | H3: Series C | I3: 8048394 | J3: N/A | K3: 1–10M | L3: =IFERROR(_xlfn.XLOOKUP(Table1[[#This Row],[Startup Name]],Reference_Tables!$A$5:$A$3048,Reference_Tables!$B$5:$B$3048,"N/A",0),"N/A") -> Gurugram | M3: =IFERROR(_xlfn.XLOOKUP(Table1[[#This Row],[Investors Name]],Reference_Tables!$E$5:$E$3048,Reference_Tables!$F$5:$F$3048,"N/A",0),"N/A") -> VC | N3: =YEAR(Table1[[#This Row],[Date]]) -> 2020
A4: 3 | B4: 43839 | C4: Mamaearth | D4: E-Commerce | E4: Retailer Of Baby And Toddler Products | F4: Bangalore | G4: Sequoia Capital India | H4: Series B | I4: 18358860 | J4: N/A | K4: >10M | L4: =IFERROR(_xlfn.XLOOKUP(Table1[[#This Row],[Startup Name]],Reference_Tables!$A$5:$A$3048,Reference_Tables!$B$5:$B$3048,"N/A",0),"N/A") -> Chennai | M4: =IFERROR(_xlfn.XLOOKUP(Table1[[#This Row],[Investors Name]],Reference_Tables!$E$5:$E$3048,Reference_Tables!$F$5:$F$3048,"N/A",0),"N/A") -> VC | N4: =YEAR(Table1[[#This Row],[Date]]) -> 2020
A5: 4 | B5: 43832 | C5: Wealthbucket | D5: Fintech | E5: Online Investment | F5: Delhi | G5: Vinod Khatumal | H5: Pre-Series A | I5: 3000000 | J5: N/A | K5: 1–10M | L5: =IFERROR(_xlfn.XLOOKUP(Table1[[#This Row],[Startup Name]],Reference_Tables!$A$5:$A$3048,Reference_Tables!$B$5:$B$3048,"N/A",0),"N/A") -> Patna | M5: =IFERROR(_xlfn.XLOOKUP(Table1[[#This Row],[Investors Name]],Reference_Tables!$E$5:$E$3048,Reference_Tables!$F$5:$F$3048,"N/A",0),"N/A") -> Angel | N5: =YEAR(Table1[[#This Row],[Date]]) -> 2020
A6: 5 | B6: 43832 | C6: Fashor | D6: Fashion And Apparel | E6: Embroiled Clothes For Women | F6: Mumbai | G6: Sprout Venture Partners | H6: Seed Round | I6: 1800000 | J6: N/A | K6: 1–10M | L6: =IFERROR(_xlfn.XLOOKUP(Table1[[#This Row],[Startup Name]],Reference_Tables!$A$5:$A$3048,Reference_Tables!$B$5:$B$3048,"N/A",0),"N/A") -> Ranchi | M6: =IFERROR(_xlfn.XLOOKUP(Table1[[#This Row],[Investors Name]],Reference_Tables!$E$5:$E$3048,Reference_Tables!$F$5:$F$3048,"N/A",0),"N/A") -> VC | N6: =YEAR(Table1[[#This Row],[Date]]) -> 2020
A7: 6 | B7: 43843 | C7: Pando | D7: Logistics | E7: Open-Market, Freight Management Platform | F7: Chennai | G7: Chiratae Ventures | H7: Series A | I7: 9000000 | J7: N/A | K7: 1–10M | L7: =IFERROR(_xlfn.XLOOKUP(Table1[[#This Row],[Startup Name]],Reference_Tables!$A$5:$A$3048,Reference_Tables!$B$5:$B$3048,"N/A",0),"N/A") -> Lucknow | M7: =IFERROR(_xlfn.XLOOKUP(Table1[[#This Row],[Investors Name]],Reference_Tables!$E$5:$E$3048,Reference_Tables!$F$5:$F$3048,"N/A",0),"N/A") -> VC | N7: =YEAR(Table1[[#This Row],[Date]]) -> 2020
A8: 7 | B8: 43840 | C8: Zomato | D8: Hospitality | E8: Online Food Delivery Platform | F8: Gurugram | G8: Ant Finacial | H8: Private Equity Round | I8: 150000000 | J8: N/A | K8: >10M | L8: =IFERROR(_xlfn.XLOOKUP(Table1[[#This Row],[Startup Name]],Reference_Tables!$A$5:$A$3048,Reference_Tables!$B$5:$B$3048,"N/A",0),"N/A") -> Dehradun | M8: =IFERROR(_xlfn.XLOOKUP(Table1[[#This Row],[Investors Name]],Reference_Tables!$E$5:$E$3048,Reference_Tables!$F$5:$F$3048,"N/A",0),"N/A") -> Angel | N8: =YEAR(Table1[[#This Row],[Date]]) -> 2020
A9: 8 | B9: 43811 | C9: Ecozen | D9: Technology | E9: Agritech | F9: Pune | G9: Sathguru Catalyzer Advisors | H9: Series A | I9: 6000000 | J9: N/A | K9: 1–10M | L9: =IFERROR(_xlfn.XLOOKUP(Table1[[#This Row],[Startup Name]],Reference_Tables!$A$5:$A$3048,Reference_Tables!$B$5:$B$3048,"N/A",0),"N/A") -> Indore | M9: =IFERROR(_xlfn.XLOOKUP(Table1[[#This Row],[Investors Name]],Reference_Tables!$E$5:$E$3048,Reference_Tables!$F$5:$F$3048,"N/A",0),"N/A") -> Angel | N9: =YEAR(Table1[[#This Row],[Date]]) -> 2019
A10: 9 | B10: 43805 | C10: Cardekho | D10: E-Commerce | E10: Automobile | F10: Gurugram | G10: Ping An Global Voyager Fund | H10: Series D | I10: 70000000 | J10: N/A | K10: >10M | L10: =IFERROR(_xlfn.XLOOKUP(Table1[[#This Row],[Startup Name]],Reference_Tables!$A$5:$A$3048,Reference_Tables!$B$5:$B$3048,"N/A",0),"N/A") -> Ranchi | M10: =IFERROR(_xlfn.XLOOKUP(Table1[[#This Row],[Investors Name]],Reference_Tables!$E$5:$E$3048,Reference_Tables!$F$5:$F$3048,"N/A",0),"N/A") -> VC | N10: =YEAR(Table1[[#This Row],[Date]]) -> 2019
A11: 10 | B11: 43802 | C11: Dhruva Space | D11: Aerospace | E11: Satellite Communication | F11: Bangalore | G11: Mumbai Angels, Ravikanth Reddy | H11: Seed | I11: 50000000 | J11: N/A | K11: >10M | L11: =IFERROR(_xlfn.XLOOKUP(Table1[[#This Row],[Startup Name]],Reference_Tables!$A$5:$A$3048,Reference_Tables!$B$5:$B$3048,"N/A",0),"N/A") -> Nagpur | M11: =IFERROR(_xlfn.XLOOKUP(Table1[[#This Row],[Investors Name]],Reference_Tables!$E$5:$E$3048,Reference_Tables!$F$5:$F$3048,"N/A",0),"N/A") -> Angel | N11: =YEAR(Table1[[#This Row],[Date]]) -> 2019
A12: 11 | B12: 43812 | C12: Rivigo | D12: Technology | E12: Logistics Services And Solutions | F12: Gurugram | G12: Saif Partners, Spring Canter Investment Ltd. | H12: Series F | I12: 20000000 | J12: N/A | K12: >10M | L12: =IFERROR(_xlfn.XLOOKUP(Table1[[#This Row],[Startup Name]],Reference_Tables!$A$5:$A$3048,Reference_Tables!$B$5:$B$3048,"N/A",0),"N/A") -> Bhopal | M12: =IFERROR(_xlfn.XLOOKUP(Table1[[#This Row],[Investors Name]],Reference_Tables!$E$5:$E$3048,Reference_Tables!$F$5:$F$3048,"N/A",0),"N/A") -> VC | N12: =YEAR(Table1[[#This Row],[Date]]) -> 2019
A13: 12 | B13: 43816 | C13: Healthians | D13: B2B-Focused Foodtech Startup | E13: Food Solutions For Corporate | F13: Bangalore | G13: Paytm, Nptk, Sabre Partners And Neoplux | H13: Series C | I13: 12000000 | J13: N/A | K13: >10M | L13: =IFERROR(_xlfn.XLOOKUP(Table1[[#This Row],[Startup Name]],Reference_Tables!$A$5:$A$3048,Reference_Tables!$B$5:$B$3048,"N/A",0),"N/A") -> Chandigarh | M13: =IFERROR(_xlfn.XLOOKUP(Table1[[#This Row],[Investors Name]],Reference_Tables!$E$5:$E$3048,Reference_Tables!$F$5:$F$3048,"N/A",0),"N/A") -> VC | N13: =YEAR(Table1[[#This Row],[Date]]) -> 2019
A14: 13 | B14: 43815 | C14: Licious | D14: E-Commerce | E14: Online Meat And Seafood Ordering Startup | F14: Bangalore | G14: Vertex Growth Fund | H14: Series E | I14: 30000000 | J14: N/A | K14: >10M | L14: =IFERROR(_xlfn.XLOOKUP(Table1[[#This Row],[Startup Name]],Reference_Tables!$A$5:$A$3048,Reference_Tables!$B$5:$B$3048,"N/A",0),"N/A") -> Mysuru | M14: =IFERROR(_xlfn.XLOOKUP(Table1[[#This Row],[Investors Name]],Reference_Tables!$E$5:$E$3048,Reference_Tables!$F$5:$F$3048,"N/A",0),"N/A") -> VC | N14: =YEAR(Table1[[#This Row],[Date]]) -> 2019
A15: 14 | B15: 43815 | C15: Incred | D15: Finace | E15: Non-Banking Finacial Company | F15: Mumbai | G15: N/A | H15: Debt Funding | I15: 5900000 | J15: N/A | K15: 1–10M | L15: =IFERROR(_xlfn.XLOOKUP(Table1[[#This Row],[Startup Name]],Reference_Tables!$A$5:$A$3048,Reference_Tables!$B$5:$B$3048,"N/A",0),"N/A") -> Ahmedabad | M15: N/A | N15: =YEAR(Table1[[#This Row],[Date]]) -> 2019
A16: 15 | B16: 43813 | C16: Trell | D16: Video | E16: Experience Discovery Platform | F16: Bangalore | G16: Ruizheng Investment | H16: Seed Round | I16: 2000000 | J16: N/A | K16: 1–10M | L16: =IFERROR(_xlfn.XLOOKUP(Table1[[#This Row],[Startup Name]],Reference_Tables!$A$5:$A$3048,Reference_Tables!$B$5:$B$3048,"N/A",0),"N/A") -> Patna | M16: =IFERROR(_xlfn.XLOOKUP(Table1[[#This Row],[Investors Name]],Reference_Tables!$E$5:$E$3048,Reference_Tables!$F$5:$F$3048,"N/A",0),"N/A") -> VC | N16: =YEAR(Table1[[#This Row],[Date]]) -> 2019
A17: 16 | B17: 43810 | C17: Rein Games | D17: Gaming | E17: Real Money Based Gaming Startup | F17: Noida | G17: Manipal Education And Medical Group (Memg) | H17: Seed Round | I17: 50000000 | J17: N/A | K17: >10M | L17: =IFERROR(_xlfn.XLOOKUP(Table1[[#This Row],[Startup Name]],Reference_Tables!$A$5:$A$3048,Reference_Tables!$B$5:$B$3048,"N/A",0),"N/A") -> Bhubaneswar | M17: =IFERROR(_xlfn.XLOOKUP(Table1[[#This Row],[Investors Name]],Reference_Tables!$E$5:$E$3048,Reference_Tables!$F$5:$F$3048,"N/A",0),"N/A") -> Corporate | N17: =YEAR(Table1[[#This Row],[Date]]) -> 2019
A18: 17 | B18: 43819 | C18: Lenskart.Com | D18: E-Commerce | E18: Online Eyewear Shopping Portal | F18: Faridabad | G18: Softbank Vision Fund | H18: Series G | I18: 231000000 | J18: N/A | K18: >10M | L18: =IFERROR(_xlfn.XLOOKUP(Table1[[#This Row],[Startup Name]],Reference_Tables!$A$5:$A$3048,Reference_Tables!$B$5:$B$3048,"N/A",0),"N/A") -> Vadodara | M18: =IFERROR(_xlfn.XLOOKUP(Table1[[#This Row],[Investors Name]],Reference_Tables!$E$5:$E$3048,Reference_Tables!$F$5:$F$3048,"N/A",0),"N/A") -> VC | N18: =YEAR(Table1[[#This Row],[Date]]) -> 2019
A19: 18 | B19: 43782 | C19: Freshworks | D19: Software | E19: Business And Customer Engagement Tools | F19: San Francisco | G19: Sequoia, Capitalg, Accel | H19: Series H | I19: 150000000 | J19: N/A | K19: >10M | L19: =IFERROR(_xlfn.XLOOKUP(Table1[[#This Row],[Startup Name]],Reference_Tables!$A$5:$A$3048,Reference_Tables!$B$5:$B$3048,"N/A",0),"N/A") -> Dehradun | M19: =IFERROR(_xlfn.XLOOKUP(Table1[[#This Row],[Investors Name]],Reference_Tables!$E$5:$E$3048,Reference_Tables!$F$5:$F$3048,"N/A",0),"N/A") -> VC | N19: =YEAR(Table1[[#This Row],[Date]]) -> 2019
A20: 19 | B20: 43783 | C20: Misters | D20: Health And Wellness | E20: Men'S Health And Wellness Brand | F20: Gurugram | G20: Sauce.Vc, Rainforest Ventures | H20: Series B | I20: 486000 | J20: N/A | K20: <1M | L20: =IFERROR(_xlfn.XLOOKUP(Table1[[#This Row],[Startup Name]],Reference_Tables!$A$5:$A$3048,Reference_Tables!$B$5:$B$3048,"N/A",0),"N/A") -> Mysuru | M20: =IFERROR(_xlfn.XLOOKUP(Table1[[#This Row],[Investors Name]],Reference_Tables!$E$5:$E$3048,Reference_Tables!$F$5:$F$3048,"N/A",0),"N/A") -> VC | N20: =YEAR(Table1[[#This Row],[Date]]) -> 2019
A21: 20 | B21: 43782 | C21: Sunstone Eduversity Pvt. Ltd | D21: Education | E21: Elearning | F21: Gurugram | G21: Prime Venture Partners, Letsventure, Ps1 Venture And Globallogic Co-Founder Rajul Garg | H21: Seed | I21: 1500000 | J21: N/A | K21: 1–10M | L21: =IFERROR(_xlfn.XLOOKUP(Table1[[#This Row],[Startup Name]],Reference_Tables!$A$5:$A$3048,Reference_Tables!$B$5:$B$3048,"N/A",0),"N/A") -> Ahmedabad | M21: =IFERROR(_xlfn.XLOOKUP(Table1[[#This Row],[Investors Name]],Reference_Tables!$E$5:$E$3048,Reference_Tables!$F$5:$F$3048,"N/A",0),"N/A") -> VC | N21: =YEAR(Table1[[#This Row],[Date]]) -> 2019
A22: 21 | B22: 43786 | C22: Burger Singh | D22: Food And Beverage | E22: Indian Burger Brand | F22: Gurugram | G22: Rb Investments | H22: Venture | I22: 0 | J22: N/A | K22: N/A | L22: =IFERROR(_xlfn.XLOOKUP(Table1[[#This Row],[Startup Name]],Reference_Tables!$A$5:$A$3048,Reference_Tables!$B$5:$B$3048,"N/A",0),"N/A") -> Visakhapatnam | M22: =IFERROR(_xlfn.XLOOKUP(Table1[[#This Row],[Investors Name]],Reference_Tables!$E$5:$E$3048,Reference_Tables!$F$5:$F$3048,"N/A",0),"N/A") -> VC | N22: =YEAR(Table1[[#This Row],[Date]]) -> 2019
A23: 22 | B23: 43787 | C23: Healthians | D23: Health And Wellness | E23: Healthcare Services | F23: Gurugram | G23: Dg Daiwa Ventures, Dg Incubation | H23: Series B | I23: 12000000 | J23: N/A | K23: >10M | L23: =IFERROR(_xlfn.XLOOKUP(Table1[[#This Row],[Startup Name]],Reference_Tables!$A$5:$A$3048,Reference_Tables!$B$5:$B$3048,"N/A",0),"N/A") -> Chandigarh | M23: =IFERROR(_xlfn.XLOOKUP(Table1[[#This Row],[Investors Name]],Reference_Tables!$E$5:$E$3048,Reference_Tables!$F$5:$F$3048,"N/A",0),"N/A") -> VC | N23: =YEAR(Table1[[#This Row],[Date]]) -> 2019
A24: 23 | B24: 43784 | C24: Ninjacart | D24: B2B Marketing | E24: Agritech | F24: Bangalore | G24: Trifecta Capital Advisors | H24: Debt Funding | I24: 26000000 | J24: N/A | K24: >10M | L24: =IFERROR(_xlfn.XLOOKUP(Table1[[#This Row],[Startup Name]],Reference_Tables!$A$5:$A$3048,Reference_Tables!$B$5:$B$3048,"N/A",0),"N/A") -> Mumbai | M24: =IFERROR(_xlfn.XLOOKUP(Table1[[#This Row],[Investors Name]],Reference_Tables!$E$5:$E$3048,Reference_Tables!$F$5:$F$3048,"N/A",0),"N/A") -> VC | N24: =YEAR(Table1[[#This Row],[Date]]) -> 2019
A25: 24 | B25: 43789 | C25: Aye Finace | D25: Fintech | E25: Finacial Services To Msmes | F25: Gurugram | G25: Fintech | H25: Debt Funding | I25: 17411265 | J25: N/A | K25: >10M | L25: =IFERROR(_xlfn.XLOOKUP(Table1[[#This Row],[Startup Name]],Reference_Tables!$A$5:$A$3048,Reference_Tables!$B$5:$B$3048,"N/A",0),"N/A") -> Nagpur | M25: =IFERROR(_xlfn.XLOOKUP(Table1[[#This Row],[Investors Name]],Reference_Tables!$E$5:$E$3048,Reference_Tables!$F$5:$F$3048,"N/A",0),"N/A") -> Angel | N25: =YEAR(Table1[[#This Row],[Date]]) -> 2019
A26: 25 | B26: 43781 | C26: Supergaming | D26: Video Games | E26: Social Gaming Platform | F26: Pune | G26: Dream Incubator | H26: Seed Funding | I26: 1300000 | J26: N/A | K26: 1–10M | L26: =IFERROR(_xlfn.XLOOKUP(Table1[[#This Row],[Startup Name]],Reference_Tables!$A$5:$A$3048,Reference_Tables!$B$5:$B$3048,"N/A",0),"N/A") -> Kolkata | M26: =IFERROR(_xlfn.XLOOKUP(Table1[[#This Row],[Investors Name]],Reference_Tables!$E$5:$E$3048,Reference_Tables!$F$5:$F$3048,"N/A",0),"N/A") -> Angel | N26: =YEAR(Table1[[#This Row],[Date]]) -> 2019
A27: 26 | B27: 43789 | C27: Clumio | D27: Saas | E27: Recovery Software | F27: San Jose, | G27: Altimeter Capital, Sutter Hill Ventures | H27: Series C | I27: 135000000 | J27: N/A | K27: >10M | L27: =IFERROR(_xlfn.XLOOKUP(Table1[[#This Row],[Startup Name]],Reference_Tables!$A$5:$A$3048,Reference_Tables!$B$5:$B$3048,"N/A",0),"N/A") -> Guwahati | M27: =IFERROR(_xlfn.XLOOKUP(Table1[[#This Row],[Investors Name]],Reference_Tables!$E$5:$E$3048,Reference_Tables!$F$5:$F$3048,"N/A",0),"N/A") -> VC | N27: =YEAR(Table1[[#This Row],[Date]]) -> 2019
... A47: 46 | B47: 43678 | C47: Progcap | D47: Finace | E47: Supply Chain Management | F47: Delhi | G47: Sequoia India | H47: Series A | I47: 5000000 | J47: N/A | K47: 1–10M | L47: =IFERROR(_xlfn.XLOOKUP(Table1[[#This Row],[Startup Name]],Reference_Tables!$A$5:$A$3048,Reference_Tables!$B$5:$B$3048,"N/A",0),"N/A") -> Dehradun | M47: =IFERROR(_xlfn.XLOOKUP(Table1[[#This Row],[Investors Name]],Reference_Tables!$E$5:$E$3048,Reference_Tables!$F$5:$F$3048,"N/A",0),"N/A") -> Angel | N47: =YEAR(Table1[[#This Row],[Date]]) -> 2019
A48: 47 | B48: 43678 | C48: Mypetrolpump | D48: Retail | E48: Fuel Delivery | F48: Bangalore | G48: N/A | H48: Seed Funding Round | I48: 1600000 | J48: N/A | K48: 1–10M | L48: =IFERROR(_xlfn.XLOOKUP(Table1[[#This Row],[Startup Name]],Reference_Tables!$A$5:$A$3048,Reference_Tables!$B$5:$B$3048,"N/A",0),"N/A") -> Coimbatore | M48: N/A | N48: =YEAR(Table1[[#This Row],[Date]]) -> 2019
A49: 48 | B49: 43678 | C49: Alteria Capital | D49: Finace | E49: Vc Funds | F49: Mumbai | G49: Azim Premji, Binny Bansal | H49: Single Venture | I49: 140000000 | J49: N/A | K49: >10M | L49: =IFERROR(_xlfn.XLOOKUP(Table1[[#This Row],[Startup Name]],Reference_Tables!$A$5:$A$3048,Reference_Tables!$B$5:$B$3048,"N/A",0),"N/A") -> Kanpur | M49: =IFERROR(_xlfn.XLOOKUP(Table1[[#This Row],[Investors Name]],Reference_Tables!$E$5:$E$3048,Reference_Tables!$F$5:$F$3048,"N/A",0),"N/A") -> Angel | N49: =YEAR(Table1[[#This Row],[Date]]) -> 2019
A50: 49 | B50: 43678 | C50: Pine Labs | D50: Information Technology | E50: Last-Mile Retail Transaction Technology | F50: Noida | G50: Pine Labs Pte Ltd | H50: Corporate Round | I50: 38080000 | J50: N/A | K50: >10M | L50: =IFERROR(_xlfn.XLOOKUP(Table1[[#This Row],[Startup Name]],Reference_Tables!$A$5:$A$3048,Reference_Tables!$B$5:$B$3048,"N/A",0),"N/A") -> Visakhapatnam | M50: =IFERROR(_xlfn.XLOOKUP(Table1[[#This Row],[Investors Name]],Reference_Tables!$E$5:$E$3048,Reference_Tables!$F$5:$F$3048,"N/A",0),"N/A") -> Corporate | N50: =YEAR(Table1[[#This Row],[Date]]) -> 2019
A51: 50 | B51: 43689 | C51: Meesho | D51: E-Commerce | E51: Social Commerce | F51: Bangalore | G51: Naspers | H51: Series D | I51: 125000000 | J51: N/A | K51: >10M | L51: =IFERROR(_xlfn.XLOOKUP(Table1[[#This Row],[Startup Name]],Reference_Tables!$A$5:$A$3048,Reference_Tables!$B$5:$B$3048,"N/A",0),"N/A") -> Vadodara | M51: =IFERROR(_xlfn.XLOOKUP(Table1[[#This Row],[Investors Name]],Reference_Tables!$E$5:$E$3048,Reference_Tables!$F$5:$F$3048,"N/A",0),"N/A") -> Corporate | N51: =YEAR(Table1[[#This Row],[Date]]) -> 2019
A52: 51 | B52: 43690 | C52: Cars24 | D52: E-Commerce | E52: Car Retail | F52: Gurugram | G52: Ms Dhoni | H52: Series D | I52: 11000000 | J52: N/A | K52: >10M | L52: =IFERROR(_xlfn.XLOOKUP(Table1[[#This Row],[Startup Name]],Reference_Tables!$A$5:$A$3048,Reference_Tables!$B$5:$B$3048,"N/A",0),"N/A") -> Noida | M52: =IFERROR(_xlfn.XLOOKUP(Table1[[#This Row],[Investors Name]],Reference_Tables!$E$5:$E$3048,Reference_Tables!$F$5:$F$3048,"N/A",0),"N/A") -> Angel | N52: =YEAR(Table1[[#This Row],[Date]]) -> 2019
A53: 52 | B53: 43690 | C53: Uniphore | D53: Customer Service Platform | E53: Conversational Ai | F53: Palo Alto | G53: March Capital Partners | H53: Series C | I53: 51000000 | J53: N/A | K53: >10M | L53: =IFERROR(_xlfn.XLOOKUP(Table1[[#This Row],[Startup Name]],Reference_Tables!$A$5:$A$3048,Reference_Tables!$B$5:$B$3048,"N/A",0),"N/A") -> Bhubaneswar | M53: =IFERROR(_xlfn.XLOOKUP(Table1[[#This Row],[Investors Name]],Reference_Tables!$E$5:$E$3048,Reference_Tables!$F$5:$F$3048,"N/A",0),"N/A") -> VC | N53: =YEAR(Table1[[#This Row],[Date]]) -> 2019
A54: 53 | B54: 43700 | C54: Zendrive | D54: Automotive | E54: Road Safety Analytics | F54: San Francisco | G54: Xl Innovate | H54: Series B | I54: 37000000 | J54: N/A | K54: >10M | L54: =IFERROR(_xlfn.XLOOKUP(Table1[[#This Row],[Startup Name]],Reference_Tables!$A$5:$A$3048,Reference_Tables!$B$5:$B$3048,"N/A",0),"N/A") -> Mysuru | M54: =IFERROR(_xlfn.XLOOKUP(Table1[[#This Row],[Investors Name]],Reference_Tables!$E$5:$E$3048,Reference_Tables!$F$5:$F$3048,"N/A",0),"N/A") -> Angel | N54: =YEAR(Table1[[#This Row],[Date]]) -> 2019
A55: 54 | B55: 43700 | C55: Lo! Foods | D55: Consumer Goods | E55: Low Carb Food For Diabetics | F55: Bangalore | G55: Rashmi Daga (Founder, Freshmenu), Raveen Sastry (Co-Founder, Myntra) And Mitesh Shah (Finace Chief, Bookmyshow) | H55: Seed Round | I55: 500000 | J55: N/A | K55: <1M | L55: =IFERROR(_xlfn.XLOOKUP(Table1[[#This Row],[Startup Name]],Reference_Tables!$A$5:$A$3048,Reference_Tables!$B$5:$B$3048,"N/A",0),"N/A") -> New Delhi | M55: N/A | N55: =YEAR(Table1[[#This Row],[Date]]) -> 2019
A56: 55 | B56: 43700 | C56: Tala | D56: Fintech | E56: Digital Lending Platform | F56: Santa Monica | G56: Rps Ventures | H56: Series D | I56: 110000000 | J56: N/A | K56: >10M | L56: =IFERROR(_xlfn.XLOOKUP(Table1[[#This Row],[Startup Name]],Reference_Tables!$A$5:$A$3048,Reference_Tables!$B$5:$B$3048,"N/A",0),"N/A") -> Kochi | M56: =IFERROR(_xlfn.XLOOKUP(Table1[[#This Row],[Investors Name]],Reference_Tables!$E$5:$E$3048,Reference_Tables!$F$5:$F$3048,"N/A",0),"N/A") -> VC | N56: =YEAR(Table1[[#This Row],[Date]]) -> 2019
A57: 56 | B57: 43699 | C57: Indwealth | D57: Fintech | E57: Wealth Management | F57: Gurugram | G57: Tiger Global Management | H57: Venture Round | I57: 15000000 | J57: N/A | K57: >10M | L57: =IFERROR(_xlfn.XLOOKUP(Table1[[#This Row],[Startup Name]],Reference_Tables!$A$5:$A$3048,Reference_Tables!$B$5:$B$3048,"N/A",0),"N/A") -> Chandigarh | M57: =IFERROR(_xlfn.XLOOKUP(Table1[[#This Row],[Investors Name]],Reference_Tables!$E$5:$E$3048,Reference_Tables!$F$5:$F$3048,"N/A",0),"N/A") -> Angel | N57: =YEAR(Table1[[#This Row],[Date]]) -> 2019
A58: 57 | B58: 43698 | C58: Hungerbox | D58: Food And Beverage | E58: B2B Foodtech | F58: Bangalore | G58: One97 Communications Ltd. | H58: Series C | I58: 6590000 | J58: N/A | K58: 1–10M | L58: =IFERROR(_xlfn.XLOOKUP(Table1[[#This Row],[Startup Name]],Reference_Tables!$A$5:$A$3048,Reference_Tables!$B$5:$B$3048,"N/A",0),"N/A") -> Mumbai | M58: =IFERROR(_xlfn.XLOOKUP(Table1[[#This Row],[Investors Name]],Reference_Tables!$E$5:$E$3048,Reference_Tables!$F$5:$F$3048,"N/A",0),"N/A") -> Corporate | N58: =YEAR(Table1[[#This Row],[Date]]) -> 2019
A59: 58 | B59: 43700 | C59: Admitkard | D59: Edtech | E59: University Admissions | F59: Noida | G59: Growth Dna | H59: Seed Round | I59: 1000000 | J59: N/A | K59: 1–10M | L59: =IFERROR(_xlfn.XLOOKUP(Table1[[#This Row],[Startup Name]],Reference_Tables!$A$5:$A$3048,Reference_Tables!$B$5:$B$3048,"N/A",0),"N/A") -> Jaipur | M59: =IFERROR(_xlfn.XLOOKUP(Table1[[#This Row],[Investors Name]],Reference_Tables!$E$5:$E$3048,Reference_Tables!$F$5:$F$3048,"N/A",0),"N/A") -> Angel | N59: =YEAR(Table1[[#This Row],[Date]]) -> 2019
A60: 59 | B60: 43696 | C60: Mishry Reviews | D60: Services | E60: Product Review | F60: Gurugram | G60: Vir Sanghvi | H60: Series A | I60: 0 | J60: N/A | K60: N/A | L60: =IFERROR(_xlfn.XLOOKUP(Table1[[#This Row],[Startup Name]],Reference_Tables!$A$5:$A$3048,Reference_Tables!$B$5:$B$3048,"N/A",0),"N/A") -> Bhubaneswar | M60: =IFERROR(_xlfn.XLOOKUP(Table1[[#This Row],[Investors Name]],Reference_Tables!$E$5:$E$3048,Reference_Tables!$F$5:$F$3048,"N/A",0),"N/A") -> Angel | N60: =YEAR(Table1[[#This Row],[Date]]) -> 2019
A61: 60 | B61: 43696 | C61: Grofers | D61: E-Commerce | E61: Grocery Delivery | F61: Gurugram | G61: Softbank Vision Fund | H61: Series F | I61: 70000000 | J61: N/A | K61: >10M | L61: =IFERROR(_xlfn.XLOOKUP(Table1[[#This Row],[Startup Name]],Reference_Tables!$A$5:$A$3048,Reference_Tables!$B$5:$B$3048,"N/A",0),"N/A") -> Gurugram | M61: =IFERROR(_xlfn.XLOOKUP(Table1[[#This Row],[Investors Name]],Reference_Tables!$E$5:$E$3048,Reference_Tables!$F$5:$F$3048,"N/A",0),"N/A") -> VC | N61: =YEAR(Table1[[#This Row],[Date]]) -> 2019
A62: 61 | B62: 43704 | C62: Rapido Bike Taxi | D62: Transportation | E62: Bike Taxi | F62: Bangalore | G62: Westbridge Capital | H62: Series B | I62: 3900000000 | J62: N/A | K62: >10M | L62: =IFERROR(_xlfn.XLOOKUP(Table1[[#This Row],[Startup Name]],Reference_Tables!$A$5:$A$3048,Reference_Tables!$B$5:$B$3048,"N/A",0),"N/A") -> Visakhapatnam | M62: =IFERROR(_xlfn.XLOOKUP(Table1[[#This Row],[Investors Name]],Reference_Tables!$E$5:$E$3048,Reference_Tables!$F$5:$F$3048,"N/A",0),"N/A") -> VC | N62: =YEAR(Table1[[#This Row],[Date]]) -> 2019
A63: 62 | B63: 43648 | C63: Renewbuy | D63: Finace | E63: Auto Insurance | F63: Gurugram | G63: Lok Capital, Iifl Wealth | H63: Series B | I63: 19000000 | J63: N/A | K63: >10M | L63: =IFERROR(_xlfn.XLOOKUP(Table1[[#This Row],[Startup Name]],Reference_Tables!$A$5:$A$3048,Reference_Tables!$B$5:$B$3048,"N/A",0),"N/A") -> Bhubaneswar | M63: =IFERROR(_xlfn.XLOOKUP(Table1[[#This Row],[Investors Name]],Reference_Tables!$E$5:$E$3048,Reference_Tables!$F$5:$F$3048,"N/A",0),"N/A") -> VC | N63: =YEAR(Table1[[#This Row],[Date]]) -> 2019
A64: 63 | B64: 43648 | C64: Atlan | D64: Information Technology | E64: Big Data | F64: Singapore | G64: Waterbridge Ventures | H64: Pre-Series A | I64: 2500000 | J64: N/A | K64: 1–10M | L64: =IFERROR(_xlfn.XLOOKUP(Table1[[#This Row],[Startup Name]],Reference_Tables!$A$5:$A$3048,Reference_Tables!$B$5:$B$3048,"N/A",0),"N/A") -> Pune | M64: =IFERROR(_xlfn.XLOOKUP(Table1[[#This Row],[Investors Name]],Reference_Tables!$E$5:$E$3048,Reference_Tables!$F$5:$F$3048,"N/A",0),"N/A") -> VC | N64: =YEAR(Table1[[#This Row],[Date]]) -> 2019
A65: 64 | B65: 43647 | C65: Wizcounsel | D65: Compliance | E65: Consulting | F65: Delhi | G65: Kapil Dev | H65: Angel | I65: 145000 | J65: N/A | K65: <1M | L65: =IFERROR(_xlfn.XLOOKUP(Table1[[#This Row],[Startup Name]],Reference_Tables!$A$5:$A$3048,Reference_Tables!$B$5:$B$3048,"N/A",0),"N/A") -> Kochi | M65: =IFERROR(_xlfn.XLOOKUP(Table1[[#This Row],[Investors Name]],Reference_Tables!$E$5:$E$3048,Reference_Tables!$F$5:$F$3048,"N/A",0),"N/A") -> Angel | N65: =YEAR(Table1[[#This Row],[Date]]) -> 2019
A66: 65 | B66: 43649 | C66: Ola Cabs | D66: Transport | E66: Cabs | F66: Kormangala | G66: Dig Investment Ab, Deshe Holdings, Samih Toukan And Hussam Khoury | H66: Series J | I66: 1000000 | J66: N/A | K66: 1–10M | L66: =IFERROR(_xlfn.XLOOKUP(Table1[[#This Row],[Startup Name]],Reference_Tables!$A$5:$A$3048,Reference_Tables!$B$5:$B$3048,"N/A",0),"N/A") -> Indore | M66: =IFERROR(_xlfn.XLOOKUP(Table1[[#This Row],[Investors Name]],Reference_Tables!$E$5:$E$3048,Reference_Tables!$F$5:$F$3048,"N/A",0),"N/A") -> VC | N66: =YEAR(Table1[[#This Row],[Date]]) -> 2019
A67: 66 | B67: 43647 | C67: Uniphore | D67: Artificial Intelligence | E67: Speech Recognition | F67: Taramani | G67: March Capital Partners | H67: Series C | I67: 38080000 | J67: N/A | K67: >10M | L67: =IFERROR(_xlfn.XLOOKUP(Table1[[#This Row],[Startup Name]],Reference_Tables!$A$5:$A$3048,Reference_Tables!$B$5:$B$3048,"N/A",0),"N/A") -> Bhubaneswar | M67: =IFERROR(_xlfn.XLOOKUP(Table1[[#This Row],[Investors Name]],Reference_Tables!$E$5:$E$3048,Reference_Tables!$F$5:$F$3048,"N/A",0),"N/A") -> VC | N67: =YEAR(Table1[[#This Row],[Date]]) -> 2019
... A112: 111 | B112: 43572 | C112: Shuttl | D112: Transportation | E112: Bus Aggregation | F112: Gurugram | G112: New Atlantic Ventures | H112: Venture Round | I112: 5000000 | J112: N/A | K112: 1–10M | L112: =IFERROR(_xlfn.XLOOKUP(Table1[[#This Row],[Startup Name]],Reference_Tables!$A$5:$A$3048,Reference_Tables!$B$5:$B$3048,"N/A",0),"N/A") -> Gurugram | M112: =IFERROR(_xlfn.XLOOKUP(Table1[[#This Row],[Investors Name]],Reference_Tables!$E$5:$E$3048,Reference_Tables!$F$5:$F$3048,"N/A",0),"N/A") -> VC | N112: =YEAR(Table1[[#This Row],[Date]]) -> 2019
A113: 112 | B113: 43572 | C113: Increff | D113: Technology | E113: Supply-Chain Technology Solutions | F113: Bangalore | G113: 021 Capita, Binny Bansal | H113: Series A | I113: 3000000 | J113: N/A | K113: 1–10M | L113: =IFERROR(_xlfn.XLOOKUP(Table1[[#This Row],[Startup Name]],Reference_Tables!$A$5:$A$3048,Reference_Tables!$B$5:$B$3048,"N/A",0),"N/A") -> Jaipur | M113: N/A | N113: =YEAR(Table1[[#This Row],[Date]]) -> 2019
A114: 113 | B114: 43497 | C114: Fleetx | D114: Ai | E114: Logistics | F114: Gurugram | G114: India Quotient And Letsventures Angel Fund | H114: Pre Series A | I114: 0 | J114: N/A | K114: N/A | L114: =IFERROR(_xlfn.XLOOKUP(Table1[[#This Row],[Startup Name]],Reference_Tables!$A$5:$A$3048,Reference_Tables!$B$5:$B$3048,"N/A",0),"N/A") -> Gurugram | M114: =IFERROR(_xlfn.XLOOKUP(Table1[[#This Row],[Investors Name]],Reference_Tables!$E$5:$E$3048,Reference_Tables!$F$5:$F$3048,"N/A",0),"N/A") -> VC | N114: =YEAR(Table1[[#This Row],[Date]]) -> 2019
A115: 114 | B115: 43504 | C115: Zilingo | D115: E-Commerce | E115: Fashion & Apparel | F115: India/Singapore | G115: Sequoia Capital And Temasek Holdings, Edbi, Burda Principal Investments, And Sofina | H115: Series D | I115: 226000000 | J115: N/A | K115: >10M | L115: =IFERROR(_xlfn.XLOOKUP(Table1[[#This Row],[Startup Name]],Reference_Tables!$A$5:$A$3048,Reference_Tables!$B$5:$B$3048,"N/A",0),"N/A") -> Bengaluru | M115: =IFERROR(_xlfn.XLOOKUP(Table1[[#This Row],[Investors Name]],Reference_Tables!$E$5:$E$3048,Reference_Tables!$F$5:$F$3048,"N/A",0),"N/A") -> VC | N115: =YEAR(Table1[[#This Row],[Date]]) -> 2019
A116: 115 | B116: 43509 | C116: naoclean Global | D116: naotechnology | E116: Anti-Pollution | F116: Delhi | G116: Letsventure, Pitchright Venture, 91Springboard, Al Nour International Holdings And Mark V Investments | H116: Series A | I116: 600000 | J116: N/A | K116: <1M | L116: =IFERROR(_xlfn.XLOOKUP(Table1[[#This Row],[Startup Name]],Reference_Tables!$A$5:$A$3048,Reference_Tables!$B$5:$B$3048,"N/A",0),"N/A") -> Ranchi | M116: =IFERROR(_xlfn.XLOOKUP(Table1[[#This Row],[Investors Name]],Reference_Tables!$E$5:$E$3048,Reference_Tables!$F$5:$F$3048,"N/A",0),"N/A") -> VC | N116: =YEAR(Table1[[#This Row],[Date]]) -> 2019
A117: 116 | B117: 43145 | C117: Oyorooms | D117: Hospitality | E117: Budget Rooms | F117: Gurugram | G117: Didi Chuxing | H117: Equity | I117: 100000000 | J117: N/A | K117: >10M | L117: =IFERROR(_xlfn.XLOOKUP(Table1[[#This Row],[Startup Name]],Reference_Tables!$A$5:$A$3048,Reference_Tables!$B$5:$B$3048,"N/A",0),"N/A") -> Jaipur | M117: =IFERROR(_xlfn.XLOOKUP(Table1[[#This Row],[Investors Name]],Reference_Tables!$E$5:$E$3048,Reference_Tables!$F$5:$F$3048,"N/A",0),"N/A") -> Angel | N117: =YEAR(Table1[[#This Row],[Date]]) -> 2018
A118: 117 | B118: 43468 | C118: Cardekho | D118: Automobile | E118: Online Marketplace | F118: Jaipur | G118: Sequoia India, Hillhouse Capital, Alphabets Growth Investment Arm Capital G And Axis Bank | H118: Series C | I118: 110000000 | J118: N/A | K118: >10M | L118: =IFERROR(_xlfn.XLOOKUP(Table1[[#This Row],[Startup Name]],Reference_Tables!$A$5:$A$3048,Reference_Tables!$B$5:$B$3048,"N/A",0),"N/A") -> Ranchi | M118: =IFERROR(_xlfn.XLOOKUP(Table1[[#This Row],[Investors Name]],Reference_Tables!$E$5:$E$3048,Reference_Tables!$F$5:$F$3048,"N/A",0),"N/A") -> VC | N118: =YEAR(Table1[[#This Row],[Date]]) -> 2019
A119: 118 | B119: 43469 | C119: Vyome Therapeutics Inc. | D119: Health And Wellness | E119: Specialty Pharmaceutical | F119: India/Us | G119: Iron Pillar, Perceptive Advisors, Romulus Capital And Kalaari Capital | H119: Series D | I119: 22000000 | J119: N/A | K119: >10M | L119: =IFERROR(_xlfn.XLOOKUP(Table1[[#This Row],[Startup Name]],Reference_Tables!$A$5:$A$3048,Reference_Tables!$B$5:$B$3048,"N/A",0),"N/A") -> Bhopal | M119: =IFERROR(_xlfn.XLOOKUP(Table1[[#This Row],[Investors Name]],Reference_Tables!$E$5:$E$3048,Reference_Tables!$F$5:$F$3048,"N/A",0),"N/A") -> VC | N119: =YEAR(Table1[[#This Row],[Date]]) -> 2019
A120: 119 | B120: 43469 | C120: Samunnati Finacial Intermediation & Services Pvt. Ltd | D120: Finace | E120: Non-Banking Finacial Company | F120: Chennai | G120: Massif, A Dutch Government Fund | H120: Debt-Funding | I120: 5000000 | J120: N/A | K120: 1–10M | L120: =IFERROR(_xlfn.XLOOKUP(Table1[[#This Row],[Startup Name]],Reference_Tables!$A$5:$A$3048,Reference_Tables!$B$5:$B$3048,"N/A",0),"N/A") -> Lucknow | M120: =IFERROR(_xlfn.XLOOKUP(Table1[[#This Row],[Investors Name]],Reference_Tables!$E$5:$E$3048,Reference_Tables!$F$5:$F$3048,"N/A",0),"N/A") -> VC | N120: =YEAR(Table1[[#This Row],[Date]]) -> 2019
A121: 120 | B121: 43438 | C121: Manch | D121: Social Media | E121: Hyperlocal Content | F121: Delhi | G121: Stellaris Venture Partners | H121: Seed Funding | I121: 700000 | J121: N/A | K121: <1M | L121: =IFERROR(_xlfn.XLOOKUP(Table1[[#This Row],[Startup Name]],Reference_Tables!$A$5:$A$3048,Reference_Tables!$B$5:$B$3048,"N/A",0),"N/A") -> Vadodara | M121: =IFERROR(_xlfn.XLOOKUP(Table1[[#This Row],[Investors Name]],Reference_Tables!$E$5:$E$3048,Reference_Tables!$F$5:$F$3048,"N/A",0),"N/A") -> VC | N121: =YEAR(Table1[[#This Row],[Date]]) -> 2018
A122: 121 | B122: 43435 | C122: Urbanclap Technologies Pvt. Ltd | D122: Services Platform | E122: Home Services Marketplace | F122: Delhi | G122: Steadview Capital And Vy Capital. | H122: Series D | I122: 50000000 | J122: N/A | K122: >10M | L122: =IFERROR(_xlfn.XLOOKUP(Table1[[#This Row],[Startup Name]],Reference_Tables!$A$5:$A$3048,Reference_Tables!$B$5:$B$3048,"N/A",0),"N/A") -> Dehradun | M122: =IFERROR(_xlfn.XLOOKUP(Table1[[#This Row],[Investors Name]],Reference_Tables!$E$5:$E$3048,Reference_Tables!$F$5:$F$3048,"N/A",0),"N/A") -> VC | N122: =YEAR(Table1[[#This Row],[Date]]) -> 2018
A123: 122 | B123: 43436 | C123: Guiddoo | D123: Travel Tech | E123: Platform For Travel Agents | F123: Mumbai | G123: Individual Investors | H123: Pre-Series A | I123: 800000 | J123: N/A | K123: <1M | L123: =IFERROR(_xlfn.XLOOKUP(Table1[[#This Row],[Startup Name]],Reference_Tables!$A$5:$A$3048,Reference_Tables!$B$5:$B$3048,"N/A",0),"N/A") -> Ranchi | M123: =IFERROR(_xlfn.XLOOKUP(Table1[[#This Row],[Investors Name]],Reference_Tables!$E$5:$E$3048,Reference_Tables!$F$5:$F$3048,"N/A",0),"N/A") -> Angel | N123: =YEAR(Table1[[#This Row],[Date]]) -> 2018
A124: 123 | B124: 43436 | C124: Career Anna | D124: Online Education | E124: Video-Based Certification, Trainings | F124: Gurugram | G124: Individual Investors | H124: Pre-Series A | I124: 572000 | J124: N/A | K124: <1M | L124: =IFERROR(_xlfn.XLOOKUP(Table1[[#This Row],[Startup Name]],Reference_Tables!$A$5:$A$3048,Reference_Tables!$B$5:$B$3048,"N/A",0),"N/A") -> Mysuru | M124: =IFERROR(_xlfn.XLOOKUP(Table1[[#This Row],[Investors Name]],Reference_Tables!$E$5:$E$3048,Reference_Tables!$F$5:$F$3048,"N/A",0),"N/A") -> Angel | N124: =YEAR(Table1[[#This Row],[Date]]) -> 2018
A125: 124 | B125: 43438 | C125: Nagpur Wholesale | D125: Online Marketplace | E125: Ecommerce | F125: Nagpur | G125: Omphalos Ventures India Llp | H125: Seed Funding | I125: 143000 | J125: N/A | K125: <1M | L125: =IFERROR(_xlfn.XLOOKUP(Table1[[#This Row],[Startup Name]],Reference_Tables!$A$5:$A$3048,Reference_Tables!$B$5:$B$3048,"N/A",0),"N/A") -> Kanpur | M125: =IFERROR(_xlfn.XLOOKUP(Table1[[#This Row],[Investors Name]],Reference_Tables!$E$5:$E$3048,Reference_Tables!$F$5:$F$3048,"N/A",0),"N/A") -> VC | N125: =YEAR(Table1[[#This Row],[Date]]) -> 2018
... A139: 138 | B139: 43425 | C139: Genius Corner | D139: Education | E139: Personalized Learning | F139: Noida | G139: Individual Investors | H139: Seed Funding | I139: 278000 | J139: N/A | K139: <1M | L139: =IFERROR(_xlfn.XLOOKUP(Table1[[#This Row],[Startup Name]],Reference_Tables!$A$5:$A$3048,Reference_Tables!$B$5:$B$3048,"N/A",0),"N/A") -> Hyderabad | M139: =IFERROR(_xlfn.XLOOKUP(Table1[[#This Row],[Investors Name]],Reference_Tables!$E$5:$E$3048,Reference_Tables!$F$5:$F$3048,"N/A",0),"N/A") -> Angel | N139: =YEAR(Table1[[#This Row],[Date]]) -> 2018
A140: 139 | B140: 43426 | C140: Aavishkaar-Intellecap Group | D140: Investment | E140: Sme Funding | F140: Mumbai | G140: Teachers Insurance And Annuity Association (Tiaa) | H140: Equity Based Funding | I140: 31000000 | J140: N/A | K140: >10M | L140: =IFERROR(_xlfn.XLOOKUP(Table1[[#This Row],[Startup Name]],Reference_Tables!$A$5:$A$3048,Reference_Tables!$B$5:$B$3048,"N/A",0),"N/A") -> Ahmedabad | M140: N/A | N140: =YEAR(Table1[[#This Row],[Date]]) -> 2018
A141: 140 | B141: 43426 | C141: Skillbox | D141: Social Network | E141: Art | F141: Gurugram | G141: Individual Investors | H141: Seed Funding | I141: 0 | J141: N/A | K141: N/A | L141: =IFERROR(_xlfn.XLOOKUP(Table1[[#This Row],[Startup Name]],Reference_Tables!$A$5:$A$3048,Reference_Tables!$B$5:$B$3048,"N/A",0),"N/A") -> Mumbai | M141: =IFERROR(_xlfn.XLOOKUP(Table1[[#This Row],[Investors Name]],Reference_Tables!$E$5:$E$3048,Reference_Tables!$F$5:$F$3048,"N/A",0),"N/A") -> Angel | N141: =YEAR(Table1[[#This Row],[Date]]) -> 2018
A142: 141 | B142: 43427 | C142: Signzy | D142: Finace Tech | E142: Digital Onboarding Solution | F142: Mumbai/Bangalore | G142: Stellaris Venture Partners And Kalaari Capital, Rajan Anadan From Google, Dilip Khandwelwal From Sap Labs India, And Amrish Rau From Payu India | H142: Series A | I142: 3400000 | J142: N/A | K142: 1–10M | L142: =IFERROR(_xlfn.XLOOKUP(Table1[[#This Row],[Startup Name]],Reference_Tables!$A$5:$A$3048,Reference_Tables!$B$5:$B$3048,"N/A",0),"N/A") -> Patna | M142: =IFERROR(_xlfn.XLOOKUP(Table1[[#This Row],[Investors Name]],Reference_Tables!$E$5:$E$3048,Reference_Tables!$F$5:$F$3048,"N/A",0),"N/A") -> VC | N142: =YEAR(Table1[[#This Row],[Date]]) -> 2018
A143: 142 | B143: 43428 | C143: Engineer.Ai | D143: Software | E143: Ai Platform | F143: India/Us | G143: Lakestar And Jungle Ventures, Softbanks Deepcore. | H143: Series A | I143: 29500000 | J143: N/A | K143: >10M | L143: =IFERROR(_xlfn.XLOOKUP(Table1[[#This Row],[Startup Name]],Reference_Tables!$A$5:$A$3048,Reference_Tables!$B$5:$B$3048,"N/A",0),"N/A") -> Indore | M143: =IFERROR(_xlfn.XLOOKUP(Table1[[#This Row],[Investors Name]],Reference_Tables!$E$5:$E$3048,Reference_Tables!$F$5:$F$3048,"N/A",0),"N/A") -> VC | N143: =YEAR(Table1[[#This Row],[Date]]) -> 2018
A144: 143 | B144: 43429 | C144: Incred Finace | D144: Finace | E144: Sme Lending | F144: India | G144: Paragon Partners, Individual Investors | H144: Private Equity | I144: 42000000 | J144: N/A | K144: >10M | L144: =IFERROR(_xlfn.XLOOKUP(Table1[[#This Row],[Startup Name]],Reference_Tables!$A$5:$A$3048,Reference_Tables!$B$5:$B$3048,"N/A",0),"N/A") -> Lucknow | M144: =IFERROR(_xlfn.XLOOKUP(Table1[[#This Row],[Investors Name]],Reference_Tables!$E$5:$E$3048,Reference_Tables!$F$5:$F$3048,"N/A",0),"N/A") -> VC | N144: =YEAR(Table1[[#This Row],[Date]]) -> 2018
A145: 144 | B145: 43429 | C145: Roposo | D145: Social Media | E145: Video Sharing | F145: Delhi | G145: Bertelsmann India Investments | H145: Series B | I145: 1700000 | J145: N/A | K145: 1–10M | L145: =IFERROR(_xlfn.XLOOKUP(Table1[[#This Row],[Startup Name]],Reference_Tables!$A$5:$A$3048,Reference_Tables!$B$5:$B$3048,"N/A",0),"N/A") -> Guwahati | M145: =IFERROR(_xlfn.XLOOKUP(Table1[[#This Row],[Investors Name]],Reference_Tables!$E$5:$E$3048,Reference_Tables!$F$5:$F$3048,"N/A",0),"N/A") -> VC | N145: =YEAR(Table1[[#This Row],[Date]]) -> 2018
A146: 145 | B146: 43374 | C146: Northmist | D146: Fashion | E146: Mens Wear | F146: Delhi | G146: Prashant Jaiswal | H146: Seed Angel Funding | I146: 0 | J146: N/A | K146: N/A | L146: =IFERROR(_xlfn.XLOOKUP(Table1[[#This Row],[Startup Name]],Reference_Tables!$A$5:$A$3048,Reference_Tables!$B$5:$B$3048,"N/A",0),"N/A") -> Surat | M146: =IFERROR(_xlfn.XLOOKUP(Table1[[#This Row],[Investors Name]],Reference_Tables!$E$5:$E$3048,Reference_Tables!$F$5:$F$3048,"N/A",0),"N/A") -> Angel | N146: =YEAR(Table1[[#This Row],[Date]]) -> 2018
A147: 146 | B147: 43375 | C147: Origo Commodities India Pvt. Ltd | D147: Logistics | E147: Supply Chain | F147: Hyderabad | G147: Cooperative Oikocredit, Caspian And Hivos-Triodos Fund | H147: Seed/ Angel Funding | I147: 11000000 | J147: N/A | K147: >10M | L147: =IFERROR(_xlfn.XLOOKUP(Table1[[#This Row],[Startup Name]],Reference_Tables!$A$5:$A$3048,Reference_Tables!$B$5:$B$3048,"N/A",0),"N/A") -> Visakhapatnam | M147: =IFERROR(_xlfn.XLOOKUP(Table1[[#This Row],[Investors Name]],Reference_Tables!$E$5:$E$3048,Reference_Tables!$F$5:$F$3048,"N/A",0),"N/A") -> VC | N147: =YEAR(Table1[[#This Row],[Date]]) -> 2018
A148: 147 | B148: 43377 | C148: Grover Zampa | D148: Food | E148: Wine | F148: Mumbai | G148: Ravi Viswanathan | H148: Private Equity | I148: 8200000 | J148: N/A | K148: 1–10M | L148: =IFERROR(_xlfn.XLOOKUP(Table1[[#This Row],[Startup Name]],Reference_Tables!$A$5:$A$3048,Reference_Tables!$B$5:$B$3048,"N/A",0),"N/A") -> Bengaluru | M148: =IFERROR(_xlfn.XLOOKUP(Table1[[#This Row],[Investors Name]],Reference_Tables!$E$5:$E$3048,Reference_Tables!$F$5:$F$3048,"N/A",0),"N/A") -> Angel | N148: =YEAR(Table1[[#This Row],[Date]]) -> 2018
A149: 148 | B149: 43378 | C149: Droom | D149: Automobile | E149: New And Used Cars Platform | F149: Gurugram | G149: Zigexn | H149: Series E | I149: 3000000 | J149: N/A | K149: 1–10M | L149: =IFERROR(_xlfn.XLOOKUP(Table1[[#This Row],[Startup Name]],Reference_Tables!$A$5:$A$3048,Reference_Tables!$B$5:$B$3048,"N/A",0),"N/A") -> Ranchi | M149: =IFERROR(_xlfn.XLOOKUP(Table1[[#This Row],[Investors Name]],Reference_Tables!$E$5:$E$3048,Reference_Tables!$F$5:$F$3048,"N/A",0),"N/A") -> Angel | N149: =YEAR(Table1[[#This Row],[Date]]) -> 2018
A150: 149 | B150: 43384 | C150: Innov8 | D150: Real Estate | E150: Co-Working | F150: Delhi | G150: Credence Family Office | H150: Pre-Series A | I150: 4000000 | J150: N/A | K150: 1–10M | L150: =IFERROR(_xlfn.XLOOKUP(Table1[[#This Row],[Startup Name]],Reference_Tables!$A$5:$A$3048,Reference_Tables!$B$5:$B$3048,"N/A",0),"N/A") -> Chandigarh | M150: =IFERROR(_xlfn.XLOOKUP(Table1[[#This Row],[Investors Name]],Reference_Tables!$E$5:$E$3048,Reference_Tables!$F$5:$F$3048,"N/A",0),"N/A") -> Angel | N150: =YEAR(Table1[[#This Row],[Date]]) -> 2018
A151: 150 | B151: 43385 | C151: Blackbuck | D151: Logistics Tech | E151: Largest Trucking Platform | F151: Bangalore | G151: Sequoia Capital India | H151: Private Funding | I151: 14680000 | J151: N/A | K151: >10M | L151: =IFERROR(_xlfn.XLOOKUP(Table1[[#This Row],[Startup Name]],Reference_Tables!$A$5:$A$3048,Reference_Tables!$B$5:$B$3048,"N/A",0),"N/A") -> Noida | M151: =IFERROR(_xlfn.XLOOKUP(Table1[[#This Row],[Investors Name]],Reference_Tables!$E$5:$E$3048,Reference_Tables!$F$5:$F$3048,"N/A",0),"N/A") -> VC | N151: =YEAR(Table1[[#This Row],[Date]]) -> 2018
A152: 151 | B152: 43385 | C152: Letstransport | D152: Logistics Tech | E152: Book Trucks Online | F152: Bangalore | G152: Fosun International | H152: Series C | I152: 12000000 | J152: N/A | K152: >10M | L152: =IFERROR(_xlfn.XLOOKUP(Table1[[#This Row],[Startup Name]],Reference_Tables!$A$5:$A$3048,Reference_Tables!$B$5:$B$3048,"N/A",0),"N/A") -> Pune | M152: =IFERROR(_xlfn.XLOOKUP(Table1[[#This Row],[Investors Name]],Reference_Tables!$E$5:$E$3048,Reference_Tables!$F$5:$F$3048,"N/A",0),"N/A") -> Angel | N152: =YEAR(Table1[[#This Row],[Date]]) -> 2018
... A155: 154 | B155: 43346 | C155: Daily Hunt | D155: Consumer Internet | E155: News And Ebooks Mobile App | F155: Bangalore | G155: Falcon Edge | H155: Private Equity | I155: 6390000 | J155: N/A | K155: 1–10M | L155: =IFERROR(_xlfn.XLOOKUP(Table1[[#This Row],[Startup Name]],Reference_Tables!$A$5:$A$3048,Reference_Tables!$B$5:$B$3048,"N/A",0),"N/A") -> Indore | M155: =IFERROR(_xlfn.XLOOKUP(Table1[[#This Row],[Investors Name]],Reference_Tables!$E$5:$E$3048,Reference_Tables!$F$5:$F$3048,"N/A",0),"N/A") -> Angel | N155: =YEAR(Table1[[#This Row],[Date]]) -> 2018
A156: 155 | B156: 43347 | C156: 3Hcare | D156: Healthcare | E156: Healthcare Service Provider | F156: Delhi | G156: N/A | H156: Seed/ Angel Funding | I156: 1000000 | J156: N/A | K156: 1–10M | L156: =IFERROR(_xlfn.XLOOKUP(Table1[[#This Row],[Startup Name]],Reference_Tables!$A$5:$A$3048,Reference_Tables!$B$5:$B$3048,"N/A",0),"N/A") -> Surat | M156: N/A | N156: =YEAR(Table1[[#This Row],[Date]]) -> 2018
A157: 156 | B157: 43347 | C157: Happygoeasy | D157: Consumer Internet | E157: Online Travel Agecy | F157: Gurugram | G157: Korea Investment Partners (Kip), Samsung And China-Based Citic Capital And Others | H157: Private Equity | I157: 0 | J157: N/A | K157: N/A | L157: =IFERROR(_xlfn.XLOOKUP(Table1[[#This Row],[Startup Name]],Reference_Tables!$A$5:$A$3048,Reference_Tables!$B$5:$B$3048,"N/A",0),"N/A") -> Thiruvananthapuram | M157: =IFERROR(_xlfn.XLOOKUP(Table1[[#This Row],[Investors Name]],Reference_Tables!$E$5:$E$3048,Reference_Tables!$F$5:$F$3048,"N/A",0),"N/A") -> VC | N157: =YEAR(Table1[[#This Row],[Date]]) -> 2018
A158: 157 | B158: 43348 | C158: Nykaa | D158: Consumer Internet | E158: Online Marketplace For Multi-Brand Beauty Cosmetic And Wellness Products | F158: Mumbai | G158: Lighthouse | H158: Private Equity | I158: 157200000 | J158: N/A | K158: >10M | L158: =IFERROR(_xlfn.XLOOKUP(Table1[[#This Row],[Startup Name]],Reference_Tables!$A$5:$A$3048,Reference_Tables!$B$5:$B$3048,"N/A",0),"N/A") -> Coimbatore | M158: =IFERROR(_xlfn.XLOOKUP(Table1[[#This Row],[Investors Name]],Reference_Tables!$E$5:$E$3048,Reference_Tables!$F$5:$F$3048,"N/A",0),"N/A") -> Angel | N158: =YEAR(Table1[[#This Row],[Date]]) -> 2018
A159: 158 | B159: 43348 | C159: Mad Street Den | D159: Technology | E159: Computer Vision And Artificial Intelligence (Ai) Platform | F159: Chennai | G159: Kddi | H159: Private Equity | I159: 0 | J159: N/A | K159: N/A | L159: =IFERROR(_xlfn.XLOOKUP(Table1[[#This Row],[Startup Name]],Reference_Tables!$A$5:$A$3048,Reference_Tables!$B$5:$B$3048,"N/A",0),"N/A") -> Mumbai | M159: =IFERROR(_xlfn.XLOOKUP(Table1[[#This Row],[Investors Name]],Reference_Tables!$E$5:$E$3048,Reference_Tables!$F$5:$F$3048,"N/A",0),"N/A") -> Angel | N159: =YEAR(Table1[[#This Row],[Date]]) -> 2018
A160: 159 | B160: 43349 | C160: Dream11 | D160: Consumer Internet | E160: Online Gaming Platform | F160: Mumbai | G160: Tencent, Kalaari Capital And Private Equity Firm Multiples Alternate Asset Management | H160: Private Equity | I160: 100000000 | J160: N/A | K160: >10M | L160: =IFERROR(_xlfn.XLOOKUP(Table1[[#This Row],[Startup Name]],Reference_Tables!$A$5:$A$3048,Reference_Tables!$B$5:$B$3048,"N/A",0),"N/A") -> Chandigarh | M160: =IFERROR(_xlfn.XLOOKUP(Table1[[#This Row],[Investors Name]],Reference_Tables!$E$5:$E$3048,Reference_Tables!$F$5:$F$3048,"N/A",0),"N/A") -> VC | N160: =YEAR(Table1[[#This Row],[Date]]) -> 2018
A161: 160 | B161: 43353 | C161: Mamaearth | D161: Healthcare | E161: Online Marketplace For Mother And Babycare Products | F161: Gurugram | G161: Stellaris Ventures & Others | H161: Private Equity | I161: 4000000 | J161: N/A | K161: 1–10M | L161: =IFERROR(_xlfn.XLOOKUP(Table1[[#This Row],[Startup Name]],Reference_Tables!$A$5:$A$3048,Reference_Tables!$B$5:$B$3048,"N/A",0),"N/A") -> Chennai | M161: =IFERROR(_xlfn.XLOOKUP(Table1[[#This Row],[Investors Name]],Reference_Tables!$E$5:$E$3048,Reference_Tables!$F$5:$F$3048,"N/A",0),"N/A") -> VC | N161: =YEAR(Table1[[#This Row],[Date]]) -> 2018
A162: 161 | B162: 43354 | C162: Autogrid | D162: Technology | E162: Ai-Based Energy Optimisation And Control Provider | F162: Bangalore | G162: Clp Holdings Group, Innogy, \\Xc3\\X98Rstead, And Tenaska | H162: Private Equity | I162: 32000000 | J162: N/A | K162: >10M | L162: =IFERROR(_xlfn.XLOOKUP(Table1[[#This Row],[Startup Name]],Reference_Tables!$A$5:$A$3048,Reference_Tables!$B$5:$B$3048,"N/A",0),"N/A") -> Indore | M162: =IFERROR(_xlfn.XLOOKUP(Table1[[#This Row],[Investors Name]],Reference_Tables!$E$5:$E$3048,Reference_Tables!$F$5:$F$3048,"N/A",0),"N/A") -> VC | N162: =YEAR(Table1[[#This Row],[Date]]) -> 2018
A163: 162 | B163: 43354 | C163: Pharmeasy | D163: Consumer Internet | E163: Online Marketplace For Pharmaceutical Products | F163: Mumbai | G163: Innoven Capital | H163: Debt Funding | I163: 5500000 | J163: N/A | K163: 1–10M | L163: =IFERROR(_xlfn.XLOOKUP(Table1[[#This Row],[Startup Name]],Reference_Tables!$A$5:$A$3048,Reference_Tables!$B$5:$B$3048,"N/A",0),"N/A") -> Vadodara | M163: =IFERROR(_xlfn.XLOOKUP(Table1[[#This Row],[Investors Name]],Reference_Tables!$E$5:$E$3048,Reference_Tables!$F$5:$F$3048,"N/A",0),"N/A") -> VC | N163: =YEAR(Table1[[#This Row],[Date]]) -> 2018
A164: 163 | B164: 43354 | C164: Upwards | D164: Fin-Tech | E164: Online Micro Lending Marketplace | F164: Mumbai | G164: Shunwei Capital,Quotient, Mayfield & Others | H164: Private Equity | I164: 5000000 | J164: N/A | K164: 1–10M | L164: =IFERROR(_xlfn.XLOOKUP(Table1[[#This Row],[Startup Name]],Reference_Tables!$A$5:$A$3048,Reference_Tables!$B$5:$B$3048,"N/A",0),"N/A") -> Kolkata | M164: =IFERROR(_xlfn.XLOOKUP(Table1[[#This Row],[Investors Name]],Reference_Tables!$E$5:$E$3048,Reference_Tables!$F$5:$F$3048,"N/A",0),"N/A") -> VC | N164: =YEAR(Table1[[#This Row],[Date]]) -> 2018
A165: 164 | B165: 43355 | C165: Kissht | D165: Fin-Tech | E165: Online Lending Platform | F165: Mumbai | G165: Vertex Ventures Southeast Asia (Sea) And India And Sistema Asia Fund, Fosun Rz Capital, Ventureast, And Endiya Partners.\\N\\N | H165: Private Equity | I165: 30000000 | J165: N/A | K165: >10M | L165: =IFERROR(_xlfn.XLOOKUP(Table1[[#This Row],[Startup Name]],Reference_Tables!$A$5:$A$3048,Reference_Tables!$B$5:$B$3048,"N/A",0),"N/A") -> Thiruvananthapuram | M165: =IFERROR(_xlfn.XLOOKUP(Table1[[#This Row],[Investors Name]],Reference_Tables!$E$5:$E$3048,Reference_Tables!$F$5:$F$3048,"N/A",0),"N/A") -> VC | N165: =YEAR(Table1[[#This Row],[Date]]) -> 2018
A166: 165 | B166: 43313 | C166: Dishq | D166: Food-Tech | E166: Personalisation Technology Firm Focusing On The Food And Beverage Industry | F166: Bangalore | G166: Farm To Fork, Arts Alliance, The Syndicate Fund, Sven Hensen, Zeroth And Artesian Venture Partners | H166: Seed/ Angel Funding | I166: 400000 | J166: N/A | K166: <1M | L166: =IFERROR(_xlfn.XLOOKUP(Table1[[#This Row],[Startup Name]],Reference_Tables!$A$5:$A$3048,Reference_Tables!$B$5:$B$3048,"N/A",0),"N/A") -> Vadodara | M166: =IFERROR(_xlfn.XLOOKUP(Table1[[#This Row],[Investors Name]],Reference_Tables!$E$5:$E$3048,Reference_Tables!$F$5:$F$3048,"N/A",0),"N/A") -> VC | N166: =YEAR(Table1[[#This Row],[Date]]) -> 2018
A167: 166 | B167: 43313 | C167: Healthfin | D167: Finace | E167: Patient Finacing Platform | F167: Pune | G167: Axilor, Sprout Venture Partners And Others | H167: Seed/ Angel Funding | I167: 0 | J167: N/A | K167: N/A | L167: =IFERROR(_xlfn.XLOOKUP(Table1[[#This Row],[Startup Name]],Reference_Tables!$A$5:$A$3048,Reference_Tables!$B$5:$B$3048,"N/A",0),"N/A") -> Ranchi | M167: =IFERROR(_xlfn.XLOOKUP(Table1[[#This Row],[Investors Name]],Reference_Tables!$E$5:$E$3048,Reference_Tables!$F$5:$F$3048,"N/A",0),"N/A") -> VC | N167: =YEAR(Table1[[#This Row],[Date]]) -> 2018
A168: 167 | B168: 43314 | C168: Samosa Labs | D168: Consumer Internet | E168: Social Media And Chat Entertainment Platform | F168: Hyderabad | G168: Xiaomi And Sequoia Capital India | H168: Private Equity | I168: 7000000 | J168: N/A | K168: 1–10M | L168: =IFERROR(_xlfn.XLOOKUP(Table1[[#This Row],[Startup Name]],Reference_Tables!$A$5:$A$3048,Reference_Tables!$B$5:$B$3048,"N/A",0),"N/A") -> Mysuru | M168: =IFERROR(_xlfn.XLOOKUP(Table1[[#This Row],[Investors Name]],Reference_Tables!$E$5:$E$3048,Reference_Tables!$F$5:$F$3048,"N/A",0),"N/A") -> VC | N168: =YEAR(Table1[[#This Row],[Date]]) -> 2018
A169: 168 | B169: 43315 | C169: Ziffyhomes | D169: Consumer Internet | E169: Online Home Rental Marketplace | F169: Gurugram | G169: Y Combinator | H169: Private Equity | I169: 120000 | J169: N/A | K169: <1M | L169: =IFERROR(_xlfn.XLOOKUP(Table1[[#This Row],[Startup Name]],Reference_Tables!$A$5:$A$3048,Reference_Tables!$B$5:$B$3048,"N/A",0),"N/A") -> Bhopal | M169: =IFERROR(_xlfn.XLOOKUP(Table1[[#This Row],[Investors Name]],Reference_Tables!$E$5:$E$3048,Reference_Tables!$F$5:$F$3048,"N/A",0),"N/A") -> Angel | N169: =YEAR(Table1[[#This Row],[Date]]) -> 2018
A170: 169 | B170: 43319 | C170: My Omnamo | D170: Consumer Internet | E170: Holy Platform Offering Customised Puja Packages To Individuals And Corporates | F170: Mumbai | G170: N/A | H170: Seed/ Angel Funding | I170: 1000000 | J170: N/A | K170: 1–10M | L170: =IFERROR(_xlfn.XLOOKUP(Table1[[#This Row],[Startup Name]],Reference_Tables!$A$5:$A$3048,Reference_Tables!$B$5:$B$3048,"N/A",0),"N/A") -> Bengaluru | M170: N/A | N170: =YEAR(Table1[[#This Row],[Date]]) -> 2018
A171: 170 | B171: 43319 | C171: Shopx | D171: Consumer Internet | E171: Assisted E-Commerce Platform | F171: Bangalore | G171: Fung Strategic Holdings | H171: Private Equity | I171: 35000000 | J171: N/A | K171: >10M | L171: =IFERROR(_xlfn.XLOOKUP(Table1[[#This Row],[Startup Name]],Reference_Tables!$A$5:$A$3048,Reference_Tables!$B$5:$B$3048,"N/A",0),"N/A") -> Bengaluru | M171: =IFERROR(_xlfn.XLOOKUP(Table1[[#This Row],[Investors Name]],Reference_Tables!$E$5:$E$3048,Reference_Tables!$F$5:$F$3048,"N/A",0),"N/A") -> VC | N171: =YEAR(Table1[[#This Row],[Date]]) -> 2018
A172: 171 | B172: 43319 | C172: Makemytrip | D172: Consumer Internet | E172: Online Travel Aggregator | F172: Gurugram | G172: Makemytrip Limited | H172: Private Equity | I172: 10000000 | J172: N/A | K172: 1–10M | L172: =IFERROR(_xlfn.XLOOKUP(Table1[[#This Row],[Startup Name]],Reference_Tables!$A$5:$A$3048,Reference_Tables!$B$5:$B$3048,"N/A",0),"N/A") -> Bengaluru | M172: =IFERROR(_xlfn.XLOOKUP(Table1[[#This Row],[Investors Name]],Reference_Tables!$E$5:$E$3048,Reference_Tables!$F$5:$F$3048,"N/A",0),"N/A") -> Corporate | N172: =YEAR(Table1[[#This Row],[Date]]) -> 2018
A173: 172 | B173: 43320 | C173: Hansel Io | D173: Consumer Internet | E173: Real-Time Mobile App Management | F173: Bangalore | G173: Vertex Ventures | H173: Seed/ Angel Funding | I173: 4000000 | J173: N/A | K173: 1–10M | L173: =IFERROR(_xlfn.XLOOKUP(Table1[[#This Row],[Startup Name]],Reference_Tables!$A$5:$A$3048,Reference_Tables!$B$5:$B$3048,"N/A",0),"N/A") -> Mumbai | M173: =IFERROR(_xlfn.XLOOKUP(Table1[[#This Row],[Investors Name]],Reference_Tables!$E$5:$E$3048,Reference_Tables!$F$5:$F$3048,"N/A",0),"N/A") -> VC | N173: =YEAR(Table1[[#This Row],[Date]]) -> 2018
A174: 173 | B174: 43320 | C174: Metro Bikes | D174: Consumer Internet | E174: Online Bike Rental Marketplace | F174: Bangalore | G174: Sequoia Capital India Advisors, Accel Partners And G Raghunadan | H174: Private Equity | I174: 12200000 | J174: N/A | K174: >10M | L174: =IFERROR(_xlfn.XLOOKUP(Table1[[#This Row],[Startup Name]],Reference_Tables!$A$5:$A$3048,Reference_Tables!$B$5:$B$3048,"N/A",0),"N/A") -> Kochi | M174: =IFERROR(_xlfn.XLOOKUP(Table1[[#This Row],[Investors Name]],Reference_Tables!$E$5:$E$3048,Reference_Tables!$F$5:$F$3048,"N/A",0),"N/A") -> VC | N174: =YEAR(Table1[[#This Row],[Date]]) -> 2018
A175: 174 | B175: 43320 | C175: Phone Pe | D175: Consumer Internet | E175: Upi Payments App | F175: Bangalore | G175: Flipkart | H175: Private Equity | I175: 66000000 | J175: N/A | K175: >10M | L175: =IFERROR(_xlfn.XLOOKUP(Table1[[#This Row],[Startup Name]],Reference_Tables!$A$5:$A$3048,Reference_Tables!$B$5:$B$3048,"N/A",0),"N/A") -> Gurugram | M175: =IFERROR(_xlfn.XLOOKUP(Table1[[#This Row],[Investors Name]],Reference_Tables!$E$5:$E$3048,Reference_Tables!$F$5:$F$3048,"N/A",0),"N/A") -> Angel | N175: =YEAR(Table1[[#This Row],[Date]]) -> 2018
A176: 175 | B176: 43321 | C176: Quizizz | D176: Ed-Tech | E176: E-Learning Platform | F176: Bangalore | G176: Nexus Venture Partners, Prime Venture Partners And Others | H176: Seed/ Angel Funding | I176: 3000000 | J176: N/A | K176: 1–10M | L176: =IFERROR(_xlfn.XLOOKUP(Table1[[#This Row],[Startup Name]],Reference_Tables!$A$5:$A$3048,Reference_Tables!$B$5:$B$3048,"N/A",0),"N/A") -> Visakhapatnam | M176: =IFERROR(_xlfn.XLOOKUP(Table1[[#This Row],[Investors Name]],Reference_Tables!$E$5:$E$3048,Reference_Tables!$F$5:$F$3048,"N/A",0),"N/A") -> VC | N176: =YEAR(Table1[[#This Row],[Date]]) -> 2018
A177: 176 | B177: 43321 | C177: Happy Emi | D177: Fin-Tech | E177: Consumer Finacing Platform | F177: Bangalore | G177: Aj Ventures And Jain International Trade Organisation (Jito) | H177: Seed/ Angel Funding | I177: 1000000 | J177: N/A | K177: 1–10M | L177: =IFERROR(_xlfn.XLOOKUP(Table1[[#This Row],[Startup Name]],Reference_Tables!$A$5:$A$3048,Reference_Tables!$B$5:$B$3048,"N/A",0),"N/A") -> Jaipur | M177: =IFERROR(_xlfn.XLOOKUP(Table1[[#This Row],[Investors Name]],Reference_Tables!$E$5:$E$3048,Reference_Tables!$F$5:$F$3048,"N/A",0),"N/A") -> VC | N177: =YEAR(Table1[[#This Row],[Date]]) -> 2018
A178: 177 | B178: 43325 | C178: Inthree | D178: Consumer Internet | E178: Rural E-Commerce Platform | F178: Chennai | G178: Ventureast, Orios Venture Partners And The Ian Fund | H178: Seed/ Angel Funding | I178: 4000000 | J178: N/A | K178: 1–10M | L178: =IFERROR(_xlfn.XLOOKUP(Table1[[#This Row],[Startup Name]],Reference_Tables!$A$5:$A$3048,Reference_Tables!$B$5:$B$3048,"N/A",0),"N/A") -> Dehradun | M178: =IFERROR(_xlfn.XLOOKUP(Table1[[#This Row],[Investors Name]],Reference_Tables!$E$5:$E$3048,Reference_Tables!$F$5:$F$3048,"N/A",0),"N/A") -> VC | N178: =YEAR(Table1[[#This Row],[Date]]) -> 2018
...

Sheet Reference_Tables
A1: startup city dataset | E1: investor type dataset
A4: Startup Name | B4: Startup City | E4: Investor | F4: Type
A5: Byju’S | B5: Gurugram | E5: Tiger Global Management | F5: Angel
A6: Shuttl | B6: Gurugram | E6: Susquehanna Growth Equity | F6: VC
A7: Mamaearth | B7: Chennai | E7: Sequoia Capital India | F7: VC
A8: Wealthbucket | B8: Patna | E8: Vinod Khatumal | F8: Angel
A9: Fashor | B9: Ranchi | E9: Sprout Venture Partners | F9: VC
A10: Pando | B10: Lucknow | E10: Chiratae Ventures | F10: VC
A11: Zomato | B11: Dehradun | E11: Ant Finacial | F11: Angel
A12: Ecozen | B12: Indore | E12: Sathguru Catalyzer Advisors | F12: Angel
A13: Cardekho | B13: Ranchi | E13: Ping An Global Voyager Fund | F13: VC
A14: Dhruva Space | B14: Nagpur | E14: Mumbai Angels, Ravikanth Reddy | F14: Angel
A15: Rivigo | B15: Bhopal | E15: Saif Partners, Spring Canter Investment Ltd. | F15: VC
... A3048: Couponmachine.In | B3048: Gurugram | E3048: Uk Based Group Of Angel Investors | F3048: Corporate

Sheet KPI_Calculations
A1: KEY PERFORMANCE INDICATORS (KPI)
A5: Total Funding | E5: =GETPIVOTDATA("Amount in USD",Pivot_Analysis!$M$6) -> 38143914865
A8: Total Deals | E8: =COUNTA((Data_Cleaning!C2:C3045)) -> 3044
A11: Top Investor | E11: =Pivot_Analysis!E7 -> Westbridge Capital
A14: Top City | E14: =Pivot_Analysis!Q7 -> Bangalore
A17: Peak Funding Year | E17: =Pivot_Analysis!AK7 -> 2017

Sheet Pivot_Analysis
A1: Total funding by IndustryVertical | E1: Top 10 Investors by amount | I1: Funding by Range | M1: Funding by Year | Q1: Funding By City | X1: Angle vs VC Funding | AB1: Industry Share | AG1: Number of Deals by Industry | AK1: Peak Year Funding
A6: Industry Vertical | B6: Sum of Amount in USD | E6: Investors Name | F6: Sum of Amount in USD | I6: Funding Range | J6: Count of Amount in USD | M6: Year | N6: Sum of Amount in USD | Q6: City | R6: Sum of Amount in USD | X6: Investor Type | Y6: Sum of Amount in USD | AB6: Industry | AC6: Sum of Amount in USD | AG6: Industry | AH6: Count of Startup Name | AK6: Year | AL6: Sum of Amount in USD
A7: E-Commerce | B7: 8261735693 | E7: Westbridge Capital | F7: 3952000000 | I7: 1–10M | J7: 889 | M7: 2015 | N7: 8673022368 | Q7: Bangalore | R7: 18490708863 | X7: Angel | Y7: 5887811087 | AB7: B2B | AC7: 587000000 | AG7: Consumer Internet | AH7: 942 | AK7: 2017 | AL7: 10429309730
A8: Consumer Internet | B8: 6254084245 | E8: Softbank | F8: 2500000000 | I8: <1M | J8: 752 | M8: 2016 | N8: 3828088608 | Q8: Mumbai | R8: 4940535015 | X8: Corporate | Y8: 8055130095 | AB8: Consumer Internet | AC8: 6254084245 | AG8: Technology | AH8: 478 | AK8: Grand Total | AL8: 10429309730
A9: Transportation | B9: 3916632394 | E9: Softbank Group | F9: 1467000000 | I9: >10M | J9: 432 | M9: 2017 | N9: 10429309730 | Q9: Gurugram | R9: 3876913658 | X9: VC | Y9: 22694942124 | AB9: E-Commerce | AC9: 8261735693 | AG9: E-Commerce | AH9: 300
A10: Technology | B10: 2229707930 | E10: Microsoft, Ebay, Tencent Holdings | F10: 1400000000 | M10: 2018 | N10: 5122368369 | Q10: Delhi | R10: 3302171515 | X10: Grand Total | Y10: 36637883306 | AB10: E-Commerce & M-Commerce Platform | AC10: 680000000 | AG10: N/A | AH10: 171
A11: Finace | B11: 1971438000 | E11: Vijay Shekhar Sharma | F11: 1000150000 | M11: 2019 | N11: 9700918536 | Q11: Noida | R11: 1282864000 | AB11: Finace | AC11: 1971438000 | AG11: Healthcare | AH11: 71
A12: Fintech | B12: 1224211265 | E12: Steadview Capital And Existing Investors | F12: 700000000 | M12: 2020 | N12: 390207254 | Q12: N/A | R12: 1271863868 | AB12: Fintech | AC12: 1224211265 | AG12: Finace | AH12: 62
A13: Online Marketplace | B13: 700143000 | E13: Alibaba Group, Ant Finacial | F13: 680000000 | M13: Grand Total | N13: 38143914865 | Q13: Chennai | R13: 718767000 | AB13: N/A | AC13: 1231811368 | AG13: Logistics | AH13: 32
A14: E-Commerce & M-Commerce Platform | B14: 680000000 | E14: Softbank Vision Fund | F14: 601000000 | Q14: Pune | R14: 633082000 | X14: Total Angel Funding | Y14: Total VC funding | AB14: Online Marketplace | AC14: 700143000 | AG14: Education | AH14: 24
A15: B2B | B15: 587000000 | E15: Altimeter Capital, Dst Global | F15: 585000000 | Q15: Menlo Park | R15: 450000000 | X15: =Y7 -> 5887811087 | Y15: =Y10 -> 36637883306 | AB15: Technology | AC15: 2229707930 | AG15: Food & Beverage | AH15: 23
A16: Ecommerce Marketplace | B16: 500000000 | E16: Alibaba, Foxconn, Softbank | F16: 500000000 | Q16: Hyderabad | R16: 401076230 | AB16: Transportation | AC16: 3916632394 | AG16: Ed-Tech | AH16: 15
A17: Car Aggregator & Retail Mobile App | B17: 500000000 | E17: Baillie Gifford, Falcon Edge Capital, Tiger Global, Softbank Group, Dst Global, Didi Kuaidi | F17: 500000000 | Q17: California | R17: 300000000 | AG17: Fintech | AH17: 10
A18: Health And Wellness | B18: 490686000 | E18: Grand Total | F18: 13885150000 | Q18: Kormangala | R18: 284000000 | AG18: It | AH18: 8
A19: Healthcare | B19: 418218000 | Q19: Faridabad | R19: 252000000 | AG19: Others | AH19: 6
A20: Cab Aggregator | B20: 400000000 | Q20: India/Singapore | R20: 226000000 | AG20: Real Estate | AH20: 6
A21: Education | B21: 301143000 | Q21: Tulangan | R21: 200000000 | AG21: Fin-Tech | AH21: 6
A22: Food And Beverages | B22: 300311200 | Q22: San Francisco | R22: 187000000 | AG22: Food And Beverage | AH22: 6
A23: Automation | B23: 300000000 | Q23: Jaipur | R23: 152735000 | AG23: Health And Wellness | AH23: 6
A24: Last Mile Transportation | B24: 283300000 | Q24: San Jose, | R24: 135000000 | AG24: Online Education Platform | AH24: 5
A25: Hospitality | B25: 250000000 | Q25: Ahemadabad | R25: 119980811 | AG25: Edtech | AH25: 5
A26: Logistics | B26: 242845000 | Q26: Santa Monica | R26: 110000000 | AG26: Online Food Delivery | AH26: 5
A27: Cab Rental Mobile App | B27: 225000000 | Q27: Singapore | R27: 82350000 | AG27: Logistics Tech | AH27: 5
A28: B2B Platform | B28: 225000000 | Q28: Pune / Us | R28: 68500000
A29: Saas | B29: 216000000 | Q29: Delhi / Us | R29: 67000000
A30: E-Tech | B30: 200000000 | Q30: New York | R30: 52000000
A31: Software | B31: 179500000 | Q31: India/Us | R31: 51500000
A32: Automobile | B32: 164000000 | Q32: Palo Alto | R32: 51000000
A33: Edtech | B33: 157947425 | Q33: Chandigarh | R33: 47100000
A34: Transport | B34: 152000000 | Q34: India | R34: 42000000
A35: Online Classifieds | B35: 150000000 | Q35: Taramani | R35: 38080000
A36: Fin-Tech | B36: 140700000 | Q36: Surat | R36: 36230000
A37: Agtech | B37: 140000000 | Q37: India / Us | R37: 30000000
A38: Logistics Solution Provider | B38: 137000000 | Q38: Bhubneswar | R38: 23000000
A39: Online Food Delivery | B39: 121500000 | Q39: Burnsville | R39: 18000000
... A106: Mobile Point Of Sale Payment Solution | B106: 25000000 | Q106: Grand Total | R106: 38143914865
A107: Mobile Based Pos Solution | B107: 25000000
A108: Finacial Inclusion Platform | B108: 25000000
A109: Food And Beverage | B109: 22828995
A110: Tech | B110: 21750000
A111: Tele-Shopping / Ecommerce | B111: 21500000
A112: Online Wedding Marketplace | B112: 20000000
A113: Hyperlocal Shopping App | B113: 20000000
A114: Online Furniture Marketplace | B114: 20000000
A115: News Aggregator Mobile App | B115: 20000000
A116: Engineering Services Company | B116: 20000000
A117: Clinical Genomics Provider | B117: 20000000
A118: App Based Bus Pooling Services | B118: 20000000
... A805: Grand Total | B805: 36912103497

Sheet Dashboard
AK1: Sum of Amount in USD | AM1: city | AN1: Sum of Amount in USD | AQ1: Investor | AR1: Sum of Amount in USD
AK2: 38143914865 | AM2: Bengaluru | AN2: 1784517434 | AQ2: Westbridge Capital | AR2: 3952000000

Sheet Insights
A1: 📊 Business Insights – Indian Startup Funding (2015–2020)
A6: 1️⃣ Funding Growth Pattern
A7: Funding increased significantly between 2016 and 2017, indicating strong investor confidence in Indian startups. A sharp decline in 2020 reflects pandemic-driven market uncertainty.
A11: 2️⃣ Industry Dominance
A12: E-commerce and Consumer Internet sectors attract the highest funding share, highlighting strong investor preference for scalable digital business models.
A16: 3️⃣ Geographic Concentration
A17: Bengaluru leads funding significantly, reinforcing its status as India's startup capital. Funding concentration in a few cities suggests ecosystem centralization.
A21: 4️⃣ Investor Influence
A22: Westbridge Capital and Softbank dominate funding volumes, indicating high institutional investor participation.
A26: 5️⃣ Funding Structure
A27: VC investments significantly exceed Angel funding, suggesting maturity in scaling-stage investments over early-stage backing.
A31: 6️⃣ Deal Distribution
A32: Majority of deals fall within 1–10M range, reflecting mid-sized growth-stage funding rounds.
